{
  "dataset_dir": "phase_3/test_dataset",
  "model_dir": "phase_2/models_rlf_fix/final",
  "algo1": {
    "ttt_ms": 250,
    "hys_db": 4.5,
    "metrics": {
      "HOs": 4948,
      "RLFs": 1391,
      "PingPongs": 590
    }
  },
  "algo2": {
    "ttt_ms": 160,
    "hys_db": 3.0,
    "metrics": {
      "HOs": 603,
      "RLFs": 13990,
      "PingPongs": 54
    }
  },
  "ppo": {
    "init_ttt_ms": 160,
    "init_hys_db": 3.0,
    "control_interval_steps": 5,
    "metrics": {
      "HOs": 604,
      "RLFs": 13867,
      "PingPongs": 54
    }
  },
  "improvements": {
    "ppo_vs_algo1": {
      "HO_reduction_percent": 87.79304769603881,
      "RLF_reduction_percent": -896.9086987778576,
      "PingPong_reduction_percent": 90.84745762711864
    },
    "ppo_vs_algo2": {
      "HO_reduction_percent": -0.16583747927031509,
      "RLF_reduction_percent": 0.8791994281629736,
      "PingPong_reduction_percent": 0.0
    },
    "algo2_vs_algo1": {
      "HO_reduction_percent": 87.81325788197252,
      "RLF_reduction_percent": -905.7512580877067,
      "PingPong_reduction_percent": 90.84745762711864
    }
  },
  "files_evaluated": 5
}