[
  {
    "episode": 1,
    "total_reward": 21.958762767378772,
    "episode_length": 512,
    "rlf_count": 0,
    "pp_count": 0,
    "ho_count": 0,
    "avg_reward_per_step": 0.042888208530036664,
    "entropy_coef": 0.05,
    "ttt_final": 240,
    "hys_final": 2.5
  },
  {
    "episode": 2,
    "total_reward": -11.239649018457222,
    "episode_length": 512,
    "rlf_count": 0,
    "pp_count": 1,
    "ho_count": 11,
    "avg_reward_per_step": -0.02195243948917426,
    "entropy_coef": 0.049871428571428573,
    "ttt_final": 100,
    "hys_final": 3.0
  },
  {
    "episode": 3,
    "total_reward": 17.346334741393797,
    "episode_length": 512,
    "rlf_count": 0,
    "pp_count": 0,
    "ho_count": 1,
    "avg_reward_per_step": 0.03387956004178476,
    "entropy_coef": 0.049742857142857144,
    "ttt_final": 320,
    "hys_final": 5.0
  },
  {
    "episode": 4,
    "total_reward": 26.308077769708063,
    "episode_length": 512,
    "rlf_count": 0,
    "pp_count": 0,
    "ho_count": 0,
    "avg_reward_per_step": 0.05138296439396106,
    "entropy_coef": 0.049614285714285715,
    "ttt_final": 320,
    "hys_final": 5.0
  },
  {
    "episode": 5,
    "total_reward": 19.085495258849907,
    "episode_length": 512,
    "rlf_count": 0,
    "pp_count": 0,
    "ho_count": 3,
    "avg_reward_per_step": 0.037276357927441224,
    "entropy_coef": 0.049485714285714286,
    "ttt_final": 320,
    "hys_final": 4.5
  },
  {
    "episode": 6,
    "total_reward": -12.515187847138705,
    "episode_length": 512,
    "rlf_count": 0,
    "pp_count": 3,
    "ho_count": 18,
    "avg_reward_per_step": -0.024443726263942783,
    "entropy_coef": 0.04935714285714286,
    "ttt_final": 100,
    "hys_final": 2.5
  },
  {
    "episode": 7,
    "total_reward": 16.30823093631943,
    "episode_length": 512,
    "rlf_count": 0,
    "pp_count": 0,
    "ho_count": 0,
    "avg_reward_per_step": 0.031852013547498885,
    "entropy_coef": 0.049228571428571434,
    "ttt_final": 200,
    "hys_final": 4.5
  },
  {
    "episode": 8,
    "total_reward": 28.19319932384779,
    "episode_length": 512,
    "rlf_count": 0,
    "pp_count": 0,
    "ho_count": 1,
    "avg_reward_per_step": 0.055064842429390214,
    "entropy_coef": 0.049100000000000005,
    "ttt_final": 240,
    "hys_final": 2.5
  },
  {
    "episode": 9,
    "total_reward": 16.79049635169389,
    "episode_length": 512,
    "rlf_count": 0,
    "pp_count": 2,
    "ho_count": 5,
    "avg_reward_per_step": 0.03279393818690213,
    "entropy_coef": 0.048971428571428575,
    "ttt_final": 240,
    "hys_final": 2.0
  },
  {
    "episode": 10,
    "total_reward": 32.50757360618297,
    "episode_length": 512,
    "rlf_count": 0,
    "pp_count": 0,
    "ho_count": 0,
    "avg_reward_per_step": 0.06349135469957612,
    "entropy_coef": 0.048842857142857146,
    "ttt_final": 320,
    "hys_final": 3.5
  },
  {
    "episode": 11,
    "total_reward": -6.732570948596754,
    "episode_length": 512,
    "rlf_count": 0,
    "pp_count": 0,
    "ho_count": 13,
    "avg_reward_per_step": -0.013149552633978035,
    "entropy_coef": 0.04871428571428572,
    "ttt_final": 100,
    "hys_final": 3.5
  },
  {
    "episode": 12,
    "total_reward": 2.928966209751671,
    "episode_length": 53,
    "rlf_count": 0,
    "pp_count": 0,
    "ho_count": 0,
    "avg_reward_per_step": 0.05526351339154097,
    "entropy_coef": 0.04858571428571429,
    "ttt_final": 100,
    "hys_final": 4.0
  },
  {
    "episode": 13,
    "total_reward": 15.054035458710185,
    "episode_length": 512,
    "rlf_count": 0,
    "pp_count": 0,
    "ho_count": 1,
    "avg_reward_per_step": 0.02940241300529333,
    "entropy_coef": 0.04845714285714286,
    "ttt_final": 100,
    "hys_final": 3.5
  },
  {
    "episode": 14,
    "total_reward": 14.304233922055246,
    "episode_length": 512,
    "rlf_count": 0,
    "pp_count": 0,
    "ho_count": 2,
    "avg_reward_per_step": 0.027937956879014153,
    "entropy_coef": 0.04832857142857143,
    "ttt_final": 200,
    "hys_final": 5.0
  },
  {
    "episode": 15,
    "total_reward": 31.95273693265922,
    "episode_length": 512,
    "rlf_count": 0,
    "pp_count": 0,
    "ho_count": 2,
    "avg_reward_per_step": 0.06240768932160004,
    "entropy_coef": 0.0482,
    "ttt_final": 320,
    "hys_final": 4.5
  },
  {
    "episode": 16,
    "total_reward": -10.356154453532191,
    "episode_length": 512,
    "rlf_count": 0,
    "pp_count": 1,
    "ho_count": 15,
    "avg_reward_per_step": -0.02022686416705506,
    "entropy_coef": 0.04807142857142857,
    "ttt_final": 160,
    "hys_final": 5.0
  },
  {
    "episode": 17,
    "total_reward": 19.341874690642502,
    "episode_length": 512,
    "rlf_count": 0,
    "pp_count": 0,
    "ho_count": 1,
    "avg_reward_per_step": 0.03777709900516114,
    "entropy_coef": 0.04794285714285715,
    "ttt_final": 160,
    "hys_final": 5.0
  },
  {
    "episode": 18,
    "total_reward": 7.793406608840134,
    "episode_length": 512,
    "rlf_count": 0,
    "pp_count": 1,
    "ho_count": 7,
    "avg_reward_per_step": 0.015221497282890887,
    "entropy_coef": 0.04781428571428572,
    "ttt_final": 160,
    "hys_final": 5.0
  },
  {
    "episode": 19,
    "total_reward": 30.50892626422007,
    "episode_length": 512,
    "rlf_count": 0,
    "pp_count": 0,
    "ho_count": 1,
    "avg_reward_per_step": 0.05958774660980482,
    "entropy_coef": 0.04768571428571429,
    "ttt_final": 160,
    "hys_final": 3.0
  },
  {
    "episode": 20,
    "total_reward": 17.388035613068716,
    "episode_length": 512,
    "rlf_count": 0,
    "pp_count": 0,
    "ho_count": 0,
    "avg_reward_per_step": 0.033961007056774836,
    "entropy_coef": 0.04755714285714286,
    "ttt_final": 320,
    "hys_final": 5.0
  },
  {
    "episode": 21,
    "total_reward": 21.354026813495093,
    "episode_length": 512,
    "rlf_count": 0,
    "pp_count": 0,
    "ho_count": 3,
    "avg_reward_per_step": 0.0417070836201076,
    "entropy_coef": 0.04742857142857143,
    "ttt_final": 100,
    "hys_final": 4.5
  },
  {
    "episode": 22,
    "total_reward": 32.67290156541889,
    "episode_length": 512,
    "rlf_count": 0,
    "pp_count": 0,
    "ho_count": 1,
    "avg_reward_per_step": 0.06381426086995877,
    "entropy_coef": 0.0473,
    "ttt_final": 100,
    "hys_final": 4.0
  },
  {
    "episode": 23,
    "total_reward": 37.808268329730254,
    "episode_length": 512,
    "rlf_count": 0,
    "pp_count": 0,
    "ho_count": 0,
    "avg_reward_per_step": 0.0738442740815044,
    "entropy_coef": 0.04717142857142857,
    "ttt_final": 200,
    "hys_final": 5.0
  },
  {
    "episode": 24,
    "total_reward": 40.5020548700375,
    "episode_length": 512,
    "rlf_count": 0,
    "pp_count": 0,
    "ho_count": 0,
    "avg_reward_per_step": 0.07910557591804199,
    "entropy_coef": 0.04704285714285714,
    "ttt_final": 320,
    "hys_final": 5.0
  },
  {
    "episode": 25,
    "total_reward": 32.75967395962603,
    "episode_length": 512,
    "rlf_count": 0,
    "pp_count": 0,
    "ho_count": 1,
    "avg_reward_per_step": 0.06398373820239459,
    "entropy_coef": 0.046914285714285714,
    "ttt_final": 200,
    "hys_final": 4.5
  },
  {
    "episode": 26,
    "total_reward": 35.888515058749064,
    "episode_length": 512,
    "rlf_count": 0,
    "pp_count": 0,
    "ho_count": 0,
    "avg_reward_per_step": 0.07009475597411927,
    "entropy_coef": 0.04678571428571429,
    "ttt_final": 100,
    "hys_final": 2.0
  },
  {
    "episode": 27,
    "total_reward": 20.90490038264067,
    "episode_length": 319,
    "rlf_count": 0,
    "pp_count": 0,
    "ho_count": 1,
    "avg_reward_per_step": 0.06553260308037827,
    "entropy_coef": 0.04665714285714286,
    "ttt_final": 320,
    "hys_final": 5.0
  },
  {
    "episode": 28,
    "total_reward": 28.161827391176157,
    "episode_length": 512,
    "rlf_count": 0,
    "pp_count": 0,
    "ho_count": 2,
    "avg_reward_per_step": 0.05500356912339093,
    "entropy_coef": 0.04652857142857143,
    "ttt_final": 320,
    "hys_final": 3.5
  },
  {
    "episode": 29,
    "total_reward": 29.637931722440733,
    "episode_length": 512,
    "rlf_count": 0,
    "pp_count": 0,
    "ho_count": 1,
    "avg_reward_per_step": 0.05788658539539206,
    "entropy_coef": 0.046400000000000004,
    "ttt_final": 240,
    "hys_final": 5.0
  },
  {
    "episode": 30,
    "total_reward": 17.374417236142925,
    "episode_length": 379,
    "rlf_count": 0,
    "pp_count": 0,
    "ho_count": 2,
    "avg_reward_per_step": 0.04584278954127421,
    "entropy_coef": 0.046271428571428574,
    "ttt_final": 200,
    "hys_final": 3.0
  },
  {
    "episode": 31,
    "total_reward": 5.845124344840907,
    "episode_length": 512,
    "rlf_count": 0,
    "pp_count": 0,
    "ho_count": 1,
    "avg_reward_per_step": 0.011416258486017397,
    "entropy_coef": 0.046142857142857145,
    "ttt_final": 320,
    "hys_final": 3.0
  },
  {
    "episode": 32,
    "total_reward": 24.218413869479843,
    "episode_length": 512,
    "rlf_count": 0,
    "pp_count": 0,
    "ho_count": 0,
    "avg_reward_per_step": 0.04730158958882782,
    "entropy_coef": 0.046014285714285716,
    "ttt_final": 320,
    "hys_final": 4.0
  },
  {
    "episode": 33,
    "total_reward": -5.226219884938051,
    "episode_length": 512,
    "rlf_count": 0,
    "pp_count": 0,
    "ho_count": 6,
    "avg_reward_per_step": -0.010207460712769631,
    "entropy_coef": 0.04588571428571429,
    "ttt_final": 200,
    "hys_final": 2.5
  },
  {
    "episode": 34,
    "total_reward": -53.07518152853088,
    "episode_length": 512,
    "rlf_count": 0,
    "pp_count": 3,
    "ho_count": 32,
    "avg_reward_per_step": -0.10366246392291187,
    "entropy_coef": 0.04575714285714286,
    "ttt_final": 320,
    "hys_final": 3.5
  },
  {
    "episode": 35,
    "total_reward": 38.10432917645928,
    "episode_length": 512,
    "rlf_count": 0,
    "pp_count": 0,
    "ho_count": 0,
    "avg_reward_per_step": 0.07442251792277203,
    "entropy_coef": 0.04562857142857143,
    "ttt_final": 200,
    "hys_final": 5.0
  },
  {
    "episode": 36,
    "total_reward": 40.920540277254695,
    "episode_length": 512,
    "rlf_count": 0,
    "pp_count": 0,
    "ho_count": 0,
    "avg_reward_per_step": 0.07992293022901308,
    "entropy_coef": 0.0455,
    "ttt_final": 200,
    "hys_final": 5.0
  },
  {
    "episode": 37,
    "total_reward": 21.498999169923824,
    "episode_length": 512,
    "rlf_count": 0,
    "pp_count": 0,
    "ho_count": 1,
    "avg_reward_per_step": 0.04199023275375747,
    "entropy_coef": 0.045371428571428576,
    "ttt_final": 160,
    "hys_final": 4.5
  },
  {
    "episode": 38,
    "total_reward": -12.490422682011513,
    "episode_length": 512,
    "rlf_count": 0,
    "pp_count": 2,
    "ho_count": 8,
    "avg_reward_per_step": -0.024395356800803736,
    "entropy_coef": 0.04524285714285715,
    "ttt_final": 320,
    "hys_final": 4.5
  },
  {
    "episode": 39,
    "total_reward": 35.48736986995301,
    "episode_length": 512,
    "rlf_count": 0,
    "pp_count": 0,
    "ho_count": 0,
    "avg_reward_per_step": 0.06931126927725197,
    "entropy_coef": 0.04511428571428572,
    "ttt_final": 320,
    "hys_final": 5.0
  },
  {
    "episode": 40,
    "total_reward": 21.03624462625731,
    "episode_length": 512,
    "rlf_count": 0,
    "pp_count": 0,
    "ho_count": 1,
    "avg_reward_per_step": 0.04108641528565881,
    "entropy_coef": 0.04498571428571429,
    "ttt_final": 160,
    "hys_final": 5.0
  },
  {
    "episode": 41,
    "total_reward": 29.26073710517187,
    "episode_length": 512,
    "rlf_count": 0,
    "pp_count": 0,
    "ho_count": 0,
    "avg_reward_per_step": 0.05714987715853881,
    "entropy_coef": 0.04485714285714286,
    "ttt_final": 240,
    "hys_final": 5.0
  },
  {
    "episode": 42,
    "total_reward": 14.640632304107593,
    "episode_length": 512,
    "rlf_count": 0,
    "pp_count": 0,
    "ho_count": 1,
    "avg_reward_per_step": 0.02859498496896014,
    "entropy_coef": 0.04472857142857143,
    "ttt_final": 240,
    "hys_final": 5.0
  },
  {
    "episode": 43,
    "total_reward": 31.431535989037048,
    "episode_length": 512,
    "rlf_count": 0,
    "pp_count": 0,
    "ho_count": 0,
    "avg_reward_per_step": 0.061389718728587984,
    "entropy_coef": 0.0446,
    "ttt_final": 320,
    "hys_final": 5.0
  },
  {
    "episode": 44,
    "total_reward": 13.401347557993583,
    "episode_length": 512,
    "rlf_count": 0,
    "pp_count": 0,
    "ho_count": 2,
    "avg_reward_per_step": 0.026174506949206217,
    "entropy_coef": 0.04447142857142857,
    "ttt_final": 200,
    "hys_final": 4.5
  },
  {
    "episode": 45,
    "total_reward": 40.74985417443826,
    "episode_length": 512,
    "rlf_count": 0,
    "pp_count": 0,
    "ho_count": 0,
    "avg_reward_per_step": 0.07958955893444973,
    "entropy_coef": 0.04434285714285714,
    "ttt_final": 240,
    "hys_final": 4.5
  },
  {
    "episode": 46,
    "total_reward": -0.2522204119364109,
    "episode_length": 512,
    "rlf_count": 0,
    "pp_count": 2,
    "ho_count": 6,
    "avg_reward_per_step": -0.0004926179920633026,
    "entropy_coef": 0.04421428571428572,
    "ttt_final": 320,
    "hys_final": 5.0
  },
  {
    "episode": 47,
    "total_reward": -50.05355547331706,
    "episode_length": 512,
    "rlf_count": 7,
    "pp_count": 1,
    "ho_count": 14,
    "avg_reward_per_step": -0.09776085053382239,
    "entropy_coef": 0.04408571428571429,
    "ttt_final": 200,
    "hys_final": 5.0
  },
  {
    "episode": 48,
    "total_reward": -3.663919535941723,
    "episode_length": 512,
    "rlf_count": 0,
    "pp_count": 0,
    "ho_count": 8,
    "avg_reward_per_step": -0.007156092843636178,
    "entropy_coef": 0.04395714285714286,
    "ttt_final": 320,
    "hys_final": 5.0
  },
  {
    "episode": 49,
    "total_reward": 25.783729270338966,
    "episode_length": 512,
    "rlf_count": 0,
    "pp_count": 0,
    "ho_count": 1,
    "avg_reward_per_step": 0.050358846231130794,
    "entropy_coef": 0.04382857142857143,
    "ttt_final": 160,
    "hys_final": 5.0
  },
  {
    "episode": 50,
    "total_reward": -35.02809198194675,
    "episode_length": 292,
    "rlf_count": 0,
    "pp_count": 4,
    "ho_count": 24,
    "avg_reward_per_step": -0.119959219116256,
    "entropy_coef": 0.0437,
    "ttt_final": 100,
    "hys_final": 5.0
  },
  {
    "episode": 51,
    "total_reward": 36.73278700901329,
    "episode_length": 512,
    "rlf_count": 0,
    "pp_count": 0,
    "ho_count": 1,
    "avg_reward_per_step": 0.07174372462697909,
    "entropy_coef": 0.04357142857142857,
    "ttt_final": 160,
    "hys_final": 5.0
  },
  {
    "episode": 52,
    "total_reward": 14.434201087959618,
    "episode_length": 353,
    "rlf_count": 0,
    "pp_count": 0,
    "ho_count": 2,
    "avg_reward_per_step": 0.040890088067874274,
    "entropy_coef": 0.043442857142857144,
    "ttt_final": 200,
    "hys_final": 4.0
  },
  {
    "episode": 53,
    "total_reward": 41.34591702212878,
    "episode_length": 512,
    "rlf_count": 0,
    "pp_count": 0,
    "ho_count": 0,
    "avg_reward_per_step": 0.08075374418384527,
    "entropy_coef": 0.043314285714285715,
    "ttt_final": 160,
    "hys_final": 5.0
  },
  {
    "episode": 54,
    "total_reward": 7.787114633025102,
    "episode_length": 512,
    "rlf_count": 0,
    "pp_count": 3,
    "ho_count": 9,
    "avg_reward_per_step": 0.015209208267627153,
    "entropy_coef": 0.043185714285714286,
    "ttt_final": 160,
    "hys_final": 4.5
  },
  {
    "episode": 55,
    "total_reward": 35.475909019921076,
    "episode_length": 512,
    "rlf_count": 0,
    "pp_count": 0,
    "ho_count": 0,
    "avg_reward_per_step": 0.06928888480453335,
    "entropy_coef": 0.04305714285714286,
    "ttt_final": 200,
    "hys_final": 5.0
  },
  {
    "episode": 56,
    "total_reward": 13.954409215635307,
    "episode_length": 512,
    "rlf_count": 0,
    "pp_count": 1,
    "ho_count": 4,
    "avg_reward_per_step": 0.02725470549928771,
    "entropy_coef": 0.04292857142857143,
    "ttt_final": 100,
    "hys_final": 3.0
  },
  {
    "episode": 57,
    "total_reward": 1.7492629555994683,
    "episode_length": 512,
    "rlf_count": 0,
    "pp_count": 2,
    "ho_count": 8,
    "avg_reward_per_step": 0.0034165292101552116,
    "entropy_coef": 0.042800000000000005,
    "ttt_final": 320,
    "hys_final": 4.5
  },
  {
    "episode": 58,
    "total_reward": 5.4164281032315085,
    "episode_length": 512,
    "rlf_count": 0,
    "pp_count": 0,
    "ho_count": 1,
    "avg_reward_per_step": 0.01057896113912404,
    "entropy_coef": 0.042671428571428575,
    "ttt_final": 240,
    "hys_final": 5.0
  },
  {
    "episode": 59,
    "total_reward": 40.097839677137316,
    "episode_length": 512,
    "rlf_count": 0,
    "pp_count": 0,
    "ho_count": 0,
    "avg_reward_per_step": 0.07831609311940882,
    "entropy_coef": 0.042542857142857146,
    "ttt_final": 200,
    "hys_final": 4.5
  },
  {
    "episode": 60,
    "total_reward": 8.836078758664543,
    "episode_length": 242,
    "rlf_count": 0,
    "pp_count": 0,
    "ho_count": 0,
    "avg_reward_per_step": 0.036512722143241916,
    "entropy_coef": 0.04241428571428572,
    "ttt_final": 320,
    "hys_final": 5.0
  },
  {
    "episode": 61,
    "total_reward": 26.030317427247407,
    "episode_length": 512,
    "rlf_count": 0,
    "pp_count": 0,
    "ho_count": 2,
    "avg_reward_per_step": 0.05084046372509259,
    "entropy_coef": 0.04228571428571429,
    "ttt_final": 320,
    "hys_final": 5.0
  },
  {
    "episode": 62,
    "total_reward": -41.50901595575558,
    "episode_length": 512,
    "rlf_count": 8,
    "pp_count": 5,
    "ho_count": 16,
    "avg_reward_per_step": -0.08107229678858512,
    "entropy_coef": 0.04215714285714286,
    "ttt_final": 320,
    "hys_final": 5.0
  },
  {
    "episode": 63,
    "total_reward": 14.943464226270844,
    "episode_length": 512,
    "rlf_count": 0,
    "pp_count": 1,
    "ho_count": 3,
    "avg_reward_per_step": 0.029186453566935243,
    "entropy_coef": 0.04202857142857143,
    "ttt_final": 100,
    "hys_final": 3.0
  },
  {
    "episode": 64,
    "total_reward": 26.293948041367326,
    "episode_length": 416,
    "rlf_count": 0,
    "pp_count": 0,
    "ho_count": 1,
    "avg_reward_per_step": 0.06320660586867145,
    "entropy_coef": 0.0419,
    "ttt_final": 160,
    "hys_final": 4.5
  },
  {
    "episode": 65,
    "total_reward": 39.2438062453226,
    "episode_length": 512,
    "rlf_count": 0,
    "pp_count": 0,
    "ho_count": 2,
    "avg_reward_per_step": 0.07664805907289571,
    "entropy_coef": 0.04177142857142857,
    "ttt_final": 100,
    "hys_final": 4.5
  },
  {
    "episode": 66,
    "total_reward": 33.01480744281778,
    "episode_length": 512,
    "rlf_count": 0,
    "pp_count": 0,
    "ho_count": 0,
    "avg_reward_per_step": 0.06448204578675347,
    "entropy_coef": 0.04164285714285715,
    "ttt_final": 320,
    "hys_final": 2.5
  },
  {
    "episode": 67,
    "total_reward": 44.40896958846165,
    "episode_length": 512,
    "rlf_count": 0,
    "pp_count": 0,
    "ho_count": 0,
    "avg_reward_per_step": 0.08673626872746416,
    "entropy_coef": 0.04151428571428571,
    "ttt_final": 160,
    "hys_final": 3.5
  },
  {
    "episode": 68,
    "total_reward": 44.58352891752772,
    "episode_length": 512,
    "rlf_count": 0,
    "pp_count": 0,
    "ho_count": 0,
    "avg_reward_per_step": 0.08707720491704633,
    "entropy_coef": 0.04138571428571429,
    "ttt_final": 320,
    "hys_final": 2.5
  },
  {
    "episode": 69,
    "total_reward": 1.5302858296035098,
    "episode_length": 512,
    "rlf_count": 0,
    "pp_count": 1,
    "ho_count": 13,
    "avg_reward_per_step": 0.002988839510944355,
    "entropy_coef": 0.04125714285714286,
    "ttt_final": 320,
    "hys_final": 5.0
  },
  {
    "episode": 70,
    "total_reward": 23.657181354500793,
    "episode_length": 512,
    "rlf_count": 0,
    "pp_count": 0,
    "ho_count": 0,
    "avg_reward_per_step": 0.04620543233300936,
    "entropy_coef": 0.04112857142857143,
    "ttt_final": 100,
    "hys_final": 5.0
  },
  {
    "episode": 71,
    "total_reward": -67.76528986515638,
    "episode_length": 512,
    "rlf_count": 20,
    "pp_count": 3,
    "ho_count": 14,
    "avg_reward_per_step": -0.13235408176788355,
    "entropy_coef": 0.041,
    "ttt_final": 160,
    "hys_final": 5.0
  },
  {
    "episode": 72,
    "total_reward": -26.18064932557444,
    "episode_length": 512,
    "rlf_count": 0,
    "pp_count": 0,
    "ho_count": 15,
    "avg_reward_per_step": -0.05113408071401258,
    "entropy_coef": 0.04087142857142857,
    "ttt_final": 320,
    "hys_final": 5.0
  },
  {
    "episode": 73,
    "total_reward": -64.94355353889675,
    "episode_length": 512,
    "rlf_count": 16,
    "pp_count": 1,
    "ho_count": 13,
    "avg_reward_per_step": -0.12684287800565772,
    "entropy_coef": 0.04074285714285714,
    "ttt_final": 200,
    "hys_final": 4.0
  },
  {
    "episode": 74,
    "total_reward": 17.18844613946487,
    "episode_length": 512,
    "rlf_count": 0,
    "pp_count": 0,
    "ho_count": 1,
    "avg_reward_per_step": 0.03357118386614232,
    "entropy_coef": 0.040614285714285714,
    "ttt_final": 100,
    "hys_final": 4.5
  },
  {
    "episode": 75,
    "total_reward": 17.968230694467948,
    "episode_length": 512,
    "rlf_count": 0,
    "pp_count": 0,
    "ho_count": 6,
    "avg_reward_per_step": 0.03509420057513271,
    "entropy_coef": 0.040485714285714285,
    "ttt_final": 100,
    "hys_final": 5.0
  },
  {
    "episode": 76,
    "total_reward": 32.01958833639099,
    "episode_length": 512,
    "rlf_count": 0,
    "pp_count": 0,
    "ho_count": 0,
    "avg_reward_per_step": 0.06253825846951365,
    "entropy_coef": 0.040357142857142855,
    "ttt_final": 200,
    "hys_final": 4.5
  },
  {
    "episode": 77,
    "total_reward": 6.668247668291885,
    "episode_length": 512,
    "rlf_count": 0,
    "pp_count": 4,
    "ho_count": 11,
    "avg_reward_per_step": 0.013023921227132588,
    "entropy_coef": 0.04022857142857143,
    "ttt_final": 160,
    "hys_final": 4.5
  },
  {
    "episode": 78,
    "total_reward": 23.87215349595291,
    "episode_length": 512,
    "rlf_count": 0,
    "pp_count": 0,
    "ho_count": 1,
    "avg_reward_per_step": 0.04662529979678303,
    "entropy_coef": 0.040100000000000004,
    "ttt_final": 200,
    "hys_final": 5.0
  },
  {
    "episode": 79,
    "total_reward": 16.024976502884375,
    "episode_length": 512,
    "rlf_count": 0,
    "pp_count": 0,
    "ho_count": 1,
    "avg_reward_per_step": 0.031298782232196044,
    "entropy_coef": 0.039971428571428574,
    "ttt_final": 100,
    "hys_final": 5.0
  },
  {
    "episode": 80,
    "total_reward": 40.147730658645386,
    "episode_length": 512,
    "rlf_count": 0,
    "pp_count": 0,
    "ho_count": 2,
    "avg_reward_per_step": 0.07841353644266677,
    "entropy_coef": 0.039842857142857145,
    "ttt_final": 160,
    "hys_final": 5.0
  },
  {
    "episode": 81,
    "total_reward": 5.02854012109687,
    "episode_length": 512,
    "rlf_count": 0,
    "pp_count": 1,
    "ho_count": 7,
    "avg_reward_per_step": 0.009821367424017324,
    "entropy_coef": 0.039714285714285716,
    "ttt_final": 320,
    "hys_final": 4.5
  },
  {
    "episode": 82,
    "total_reward": -3.764007758573489,
    "episode_length": 512,
    "rlf_count": 0,
    "pp_count": 0,
    "ho_count": 10,
    "avg_reward_per_step": -0.007351577653463845,
    "entropy_coef": 0.03958571428571429,
    "ttt_final": 100,
    "hys_final": 5.0
  },
  {
    "episode": 83,
    "total_reward": 19.15011951022548,
    "episode_length": 512,
    "rlf_count": 0,
    "pp_count": 0,
    "ho_count": 4,
    "avg_reward_per_step": 0.03740257716840914,
    "entropy_coef": 0.03945714285714286,
    "ttt_final": 100,
    "hys_final": 5.0
  },
  {
    "episode": 84,
    "total_reward": 7.611430882095666,
    "episode_length": 168,
    "rlf_count": 0,
    "pp_count": 0,
    "ho_count": 1,
    "avg_reward_per_step": 0.045306136202950396,
    "entropy_coef": 0.03932857142857143,
    "ttt_final": 160,
    "hys_final": 5.0
  },
  {
    "episode": 85,
    "total_reward": 28.014593224980477,
    "episode_length": 512,
    "rlf_count": 0,
    "pp_count": 0,
    "ho_count": 1,
    "avg_reward_per_step": 0.05471600239253999,
    "entropy_coef": 0.0392,
    "ttt_final": 100,
    "hys_final": 5.0
  },
  {
    "episode": 86,
    "total_reward": 8.802080797112383,
    "episode_length": 159,
    "rlf_count": 0,
    "pp_count": 0,
    "ho_count": 0,
    "avg_reward_per_step": 0.05535899872397725,
    "entropy_coef": 0.039071428571428576,
    "ttt_final": 160,
    "hys_final": 5.0
  },
  {
    "episode": 87,
    "total_reward": 44.86389284105703,
    "episode_length": 512,
    "rlf_count": 0,
    "pp_count": 0,
    "ho_count": 0,
    "avg_reward_per_step": 0.08762479070518951,
    "entropy_coef": 0.03894285714285714,
    "ttt_final": 100,
    "hys_final": 4.5
  },
  {
    "episode": 88,
    "total_reward": 42.1498949827817,
    "episode_length": 512,
    "rlf_count": 0,
    "pp_count": 0,
    "ho_count": 0,
    "avg_reward_per_step": 0.08232401363824551,
    "entropy_coef": 0.03881428571428572,
    "ttt_final": 100,
    "hys_final": 5.0
  },
  {
    "episode": 89,
    "total_reward": 34.563743289044474,
    "episode_length": 512,
    "rlf_count": 0,
    "pp_count": 0,
    "ho_count": 1,
    "avg_reward_per_step": 0.06750731111141499,
    "entropy_coef": 0.03868571428571429,
    "ttt_final": 100,
    "hys_final": 5.0
  },
  {
    "episode": 90,
    "total_reward": 37.98103573983931,
    "episode_length": 512,
    "rlf_count": 0,
    "pp_count": 0,
    "ho_count": 0,
    "avg_reward_per_step": 0.07418171042937365,
    "entropy_coef": 0.03855714285714286,
    "ttt_final": 100,
    "hys_final": 5.0
  },
  {
    "episode": 91,
    "total_reward": -11.464046786870647,
    "episode_length": 512,
    "rlf_count": 0,
    "pp_count": 1,
    "ho_count": 16,
    "avg_reward_per_step": -0.02239071638060673,
    "entropy_coef": 0.03842857142857143,
    "ttt_final": 200,
    "hys_final": 5.0
  },
  {
    "episode": 92,
    "total_reward": 32.48211136986903,
    "episode_length": 512,
    "rlf_count": 0,
    "pp_count": 0,
    "ho_count": 0,
    "avg_reward_per_step": 0.06344162376927545,
    "entropy_coef": 0.0383,
    "ttt_final": 100,
    "hys_final": 4.5
  },
  {
    "episode": 93,
    "total_reward": 18.695809949254745,
    "episode_length": 512,
    "rlf_count": 0,
    "pp_count": 0,
    "ho_count": 1,
    "avg_reward_per_step": 0.03651525380713817,
    "entropy_coef": 0.03817142857142857,
    "ttt_final": 320,
    "hys_final": 4.5
  },
  {
    "episode": 94,
    "total_reward": 2.8999790010100694,
    "episode_length": 512,
    "rlf_count": 0,
    "pp_count": 0,
    "ho_count": 3,
    "avg_reward_per_step": 0.005664021486347792,
    "entropy_coef": 0.03804285714285714,
    "ttt_final": 240,
    "hys_final": 5.0
  },
  {
    "episode": 95,
    "total_reward": 10.190298378301366,
    "episode_length": 512,
    "rlf_count": 0,
    "pp_count": 1,
    "ho_count": 5,
    "avg_reward_per_step": 0.019902926520119855,
    "entropy_coef": 0.03791428571428572,
    "ttt_final": 320,
    "hys_final": 5.0
  },
  {
    "episode": 96,
    "total_reward": 39.184127750639426,
    "episode_length": 512,
    "rlf_count": 0,
    "pp_count": 0,
    "ho_count": 1,
    "avg_reward_per_step": 0.07653149951296763,
    "entropy_coef": 0.03778571428571429,
    "ttt_final": 240,
    "hys_final": 4.5
  },
  {
    "episode": 97,
    "total_reward": 21.58856603220819,
    "episode_length": 512,
    "rlf_count": 0,
    "pp_count": 0,
    "ho_count": 3,
    "avg_reward_per_step": 0.04216516803165662,
    "entropy_coef": 0.03765714285714286,
    "ttt_final": 100,
    "hys_final": 5.0
  },
  {
    "episode": 98,
    "total_reward": 16.994044456430412,
    "episode_length": 512,
    "rlf_count": 0,
    "pp_count": 0,
    "ho_count": 5,
    "avg_reward_per_step": 0.03319149307896565,
    "entropy_coef": 0.03752857142857143,
    "ttt_final": 160,
    "hys_final": 4.5
  },
  {
    "episode": 99,
    "total_reward": 24.6429669922075,
    "episode_length": 512,
    "rlf_count": 0,
    "pp_count": 0,
    "ho_count": 0,
    "avg_reward_per_step": 0.048130794906655276,
    "entropy_coef": 0.0374,
    "ttt_final": 100,
    "hys_final": 4.5
  },
  {
    "episode": 100,
    "total_reward": 7.309502388996688,
    "episode_length": 512,
    "rlf_count": 0,
    "pp_count": 1,
    "ho_count": 5,
    "avg_reward_per_step": 0.014276371853509157,
    "entropy_coef": 0.03727142857142857,
    "ttt_final": 100,
    "hys_final": 5.0
  },
  {
    "episode": 101,
    "total_reward": 21.21265959491233,
    "episode_length": 512,
    "rlf_count": 0,
    "pp_count": 1,
    "ho_count": 4,
    "avg_reward_per_step": 0.04143097577131315,
    "entropy_coef": 0.037142857142857144,
    "ttt_final": 200,
    "hys_final": 5.0
  },
  {
    "episode": 102,
    "total_reward": 12.229328952295848,
    "episode_length": 512,
    "rlf_count": 0,
    "pp_count": 0,
    "ho_count": 0,
    "avg_reward_per_step": 0.02388540810995283,
    "entropy_coef": 0.037014285714285715,
    "ttt_final": 200,
    "hys_final": 5.0
  },
  {
    "episode": 103,
    "total_reward": 23.02057363930742,
    "episode_length": 512,
    "rlf_count": 0,
    "pp_count": 0,
    "ho_count": 1,
    "avg_reward_per_step": 0.0449620578892723,
    "entropy_coef": 0.036885714285714286,
    "ttt_final": 320,
    "hys_final": 5.0
  },
  {
    "episode": 104,
    "total_reward": 17.814832799447036,
    "episode_length": 512,
    "rlf_count": 0,
    "pp_count": 0,
    "ho_count": 0,
    "avg_reward_per_step": 0.03479459531141999,
    "entropy_coef": 0.03675714285714286,
    "ttt_final": 320,
    "hys_final": 5.0
  },
  {
    "episode": 105,
    "total_reward": 35.051229100505495,
    "episode_length": 512,
    "rlf_count": 0,
    "pp_count": 0,
    "ho_count": 0,
    "avg_reward_per_step": 0.0684594318369248,
    "entropy_coef": 0.03662857142857143,
    "ttt_final": 160,
    "hys_final": 5.0
  },
  {
    "episode": 106,
    "total_reward": 12.38099888280597,
    "episode_length": 512,
    "rlf_count": 0,
    "pp_count": 0,
    "ho_count": 3,
    "avg_reward_per_step": 0.02418163844298041,
    "entropy_coef": 0.036500000000000005,
    "ttt_final": 200,
    "hys_final": 5.0
  },
  {
    "episode": 107,
    "total_reward": 48.24398049294849,
    "episode_length": 512,
    "rlf_count": 0,
    "pp_count": 0,
    "ho_count": 0,
    "avg_reward_per_step": 0.09422652440029002,
    "entropy_coef": 0.03637142857142857,
    "ttt_final": 200,
    "hys_final": 4.5
  },
  {
    "episode": 108,
    "total_reward": -4.195842342587879,
    "episode_length": 512,
    "rlf_count": 0,
    "pp_count": 0,
    "ho_count": 14,
    "avg_reward_per_step": -0.00819500457536695,
    "entropy_coef": 0.036242857142857146,
    "ttt_final": 200,
    "hys_final": 5.0
  },
  {
    "episode": 109,
    "total_reward": 19.595277754668405,
    "episode_length": 512,
    "rlf_count": 0,
    "pp_count": 0,
    "ho_count": 3,
    "avg_reward_per_step": 0.03827202686458673,
    "entropy_coef": 0.03611428571428572,
    "ttt_final": 160,
    "hys_final": 3.5
  },
  {
    "episode": 110,
    "total_reward": 39.68802395834554,
    "episode_length": 512,
    "rlf_count": 0,
    "pp_count": 0,
    "ho_count": 2,
    "avg_reward_per_step": 0.07751567179364363,
    "entropy_coef": 0.03598571428571429,
    "ttt_final": 100,
    "hys_final": 4.5
  },
  {
    "episode": 111,
    "total_reward": 28.190615145290664,
    "episode_length": 512,
    "rlf_count": 0,
    "pp_count": 0,
    "ho_count": 0,
    "avg_reward_per_step": 0.05505979520564583,
    "entropy_coef": 0.03585714285714286,
    "ttt_final": 160,
    "hys_final": 4.5
  },
  {
    "episode": 112,
    "total_reward": 45.304723919843255,
    "episode_length": 512,
    "rlf_count": 0,
    "pp_count": 0,
    "ho_count": 0,
    "avg_reward_per_step": 0.08848578890594386,
    "entropy_coef": 0.03572857142857143,
    "ttt_final": 160,
    "hys_final": 4.0
  },
  {
    "episode": 113,
    "total_reward": 27.175590938216292,
    "episode_length": 512,
    "rlf_count": 0,
    "pp_count": 0,
    "ho_count": 4,
    "avg_reward_per_step": 0.053077326051203695,
    "entropy_coef": 0.0356,
    "ttt_final": 240,
    "hys_final": 5.0
  },
  {
    "episode": 114,
    "total_reward": 25.935644106561245,
    "episode_length": 512,
    "rlf_count": 0,
    "pp_count": 0,
    "ho_count": 0,
    "avg_reward_per_step": 0.05065555489562743,
    "entropy_coef": 0.03547142857142857,
    "ttt_final": 160,
    "hys_final": 5.0
  },
  {
    "episode": 115,
    "total_reward": 23.46242192223116,
    "episode_length": 512,
    "rlf_count": 0,
    "pp_count": 0,
    "ho_count": 0,
    "avg_reward_per_step": 0.04582504281685774,
    "entropy_coef": 0.03534285714285714,
    "ttt_final": 160,
    "hys_final": 4.5
  },
  {
    "episode": 116,
    "total_reward": 19.598152405696922,
    "episode_length": 512,
    "rlf_count": 0,
    "pp_count": 0,
    "ho_count": 1,
    "avg_reward_per_step": 0.0382776414173768,
    "entropy_coef": 0.03521428571428571,
    "ttt_final": 100,
    "hys_final": 4.0
  },
  {
    "episode": 117,
    "total_reward": -43.4353216076949,
    "episode_length": 512,
    "rlf_count": 16,
    "pp_count": 2,
    "ho_count": 9,
    "avg_reward_per_step": -0.0848346125150291,
    "entropy_coef": 0.03508571428571429,
    "ttt_final": 320,
    "hys_final": 4.5
  },
  {
    "episode": 118,
    "total_reward": 13.71429058560574,
    "episode_length": 512,
    "rlf_count": 0,
    "pp_count": 0,
    "ho_count": 3,
    "avg_reward_per_step": 0.02678572380001121,
    "entropy_coef": 0.03495714285714286,
    "ttt_final": 200,
    "hys_final": 4.0
  },
  {
    "episode": 119,
    "total_reward": 14.492814048902453,
    "episode_length": 512,
    "rlf_count": 0,
    "pp_count": 0,
    "ho_count": 1,
    "avg_reward_per_step": 0.028306277439262603,
    "entropy_coef": 0.03482857142857143,
    "ttt_final": 100,
    "hys_final": 4.0
  },
  {
    "episode": 120,
    "total_reward": -18.427183877117344,
    "episode_length": 512,
    "rlf_count": 0,
    "pp_count": 0,
    "ho_count": 5,
    "avg_reward_per_step": -0.03599059350999481,
    "entropy_coef": 0.0347,
    "ttt_final": 100,
    "hys_final": 5.0
  },
  {
    "episode": 121,
    "total_reward": 31.307902110636267,
    "episode_length": 512,
    "rlf_count": 0,
    "pp_count": 0,
    "ho_count": 1,
    "avg_reward_per_step": 0.06114824630983646,
    "entropy_coef": 0.03457142857142857,
    "ttt_final": 100,
    "hys_final": 4.0
  },
  {
    "episode": 122,
    "total_reward": 26.175007282838564,
    "episode_length": 261,
    "rlf_count": 0,
    "pp_count": 0,
    "ho_count": 0,
    "avg_reward_per_step": 0.10028738422543511,
    "entropy_coef": 0.03444285714285714,
    "ttt_final": 160,
    "hys_final": 2.5
  },
  {
    "episode": 123,
    "total_reward": 16.890627816135254,
    "episode_length": 512,
    "rlf_count": 0,
    "pp_count": 0,
    "ho_count": 1,
    "avg_reward_per_step": 0.03298950745338917,
    "entropy_coef": 0.034314285714285714,
    "ttt_final": 100,
    "hys_final": 4.5
  },
  {
    "episode": 124,
    "total_reward": 44.962133569661994,
    "episode_length": 512,
    "rlf_count": 0,
    "pp_count": 0,
    "ho_count": 0,
    "avg_reward_per_step": 0.08781666712824608,
    "entropy_coef": 0.03418571428571429,
    "ttt_final": 320,
    "hys_final": 2.0
  },
  {
    "episode": 125,
    "total_reward": 50.64440458015624,
    "episode_length": 512,
    "rlf_count": 0,
    "pp_count": 0,
    "ho_count": 0,
    "avg_reward_per_step": 0.09891485269561766,
    "entropy_coef": 0.034057142857142855,
    "ttt_final": 100,
    "hys_final": 3.5
  },
  {
    "episode": 126,
    "total_reward": 22.92737648790864,
    "episode_length": 512,
    "rlf_count": 0,
    "pp_count": 0,
    "ho_count": 1,
    "avg_reward_per_step": 0.04478003220294656,
    "entropy_coef": 0.03392857142857143,
    "ttt_final": 100,
    "hys_final": 4.5
  },
  {
    "episode": 127,
    "total_reward": 13.718703025321066,
    "episode_length": 512,
    "rlf_count": 0,
    "pp_count": 0,
    "ho_count": 2,
    "avg_reward_per_step": 0.026794341846330207,
    "entropy_coef": 0.0338,
    "ttt_final": 200,
    "hys_final": 5.0
  },
  {
    "episode": 128,
    "total_reward": 18.295526936322258,
    "episode_length": 512,
    "rlf_count": 0,
    "pp_count": 0,
    "ho_count": 1,
    "avg_reward_per_step": 0.03573345104750441,
    "entropy_coef": 0.033671428571428574,
    "ttt_final": 160,
    "hys_final": 3.5
  },
  {
    "episode": 129,
    "total_reward": 25.82316540271116,
    "episode_length": 512,
    "rlf_count": 0,
    "pp_count": 0,
    "ho_count": 0,
    "avg_reward_per_step": 0.05043586992717024,
    "entropy_coef": 0.033542857142857145,
    "ttt_final": 200,
    "hys_final": 3.5
  },
  {
    "episode": 130,
    "total_reward": 15.962735568534084,
    "episode_length": 512,
    "rlf_count": 0,
    "pp_count": 1,
    "ho_count": 6,
    "avg_reward_per_step": 0.031177217907293133,
    "entropy_coef": 0.033414285714285716,
    "ttt_final": 320,
    "hys_final": 4.0
  },
  {
    "episode": 131,
    "total_reward": 36.39840657816629,
    "episode_length": 512,
    "rlf_count": 0,
    "pp_count": 0,
    "ho_count": 0,
    "avg_reward_per_step": 0.07109063784798103,
    "entropy_coef": 0.03328571428571429,
    "ttt_final": 160,
    "hys_final": 3.5
  },
  {
    "episode": 132,
    "total_reward": -7.170455777330729,
    "episode_length": 512,
    "rlf_count": 0,
    "pp_count": 0,
    "ho_count": 7,
    "avg_reward_per_step": -0.01400479644009908,
    "entropy_coef": 0.03315714285714286,
    "ttt_final": 200,
    "hys_final": 5.0
  },
  {
    "episode": 133,
    "total_reward": 43.93942043316174,
    "episode_length": 512,
    "rlf_count": 0,
    "pp_count": 0,
    "ho_count": 2,
    "avg_reward_per_step": 0.08581918053351903,
    "entropy_coef": 0.03302857142857143,
    "ttt_final": 240,
    "hys_final": 2.0
  },
  {
    "episode": 134,
    "total_reward": 2.2797505065897092,
    "episode_length": 512,
    "rlf_count": 0,
    "pp_count": 0,
    "ho_count": 1,
    "avg_reward_per_step": 0.004452637708183026,
    "entropy_coef": 0.0329,
    "ttt_final": 100,
    "hys_final": 4.5
  },
  {
    "episode": 135,
    "total_reward": 19.33368549963845,
    "episode_length": 512,
    "rlf_count": 0,
    "pp_count": 0,
    "ho_count": 0,
    "avg_reward_per_step": 0.037761104491481345,
    "entropy_coef": 0.032771428571428576,
    "ttt_final": 200,
    "hys_final": 4.5
  },
  {
    "episode": 136,
    "total_reward": -10.974339223441106,
    "episode_length": 512,
    "rlf_count": 0,
    "pp_count": 1,
    "ho_count": 8,
    "avg_reward_per_step": -0.02143425629578341,
    "entropy_coef": 0.03264285714285714,
    "ttt_final": 240,
    "hys_final": 5.0
  },
  {
    "episode": 137,
    "total_reward": 43.65116915518729,
    "episode_length": 512,
    "rlf_count": 0,
    "pp_count": 0,
    "ho_count": 2,
    "avg_reward_per_step": 0.08525618975622518,
    "entropy_coef": 0.03251428571428572,
    "ttt_final": 200,
    "hys_final": 3.0
  },
  {
    "episode": 138,
    "total_reward": 19.809596369551063,
    "episode_length": 512,
    "rlf_count": 0,
    "pp_count": 0,
    "ho_count": 3,
    "avg_reward_per_step": 0.03869061790927942,
    "entropy_coef": 0.03238571428571429,
    "ttt_final": 240,
    "hys_final": 5.0
  },
  {
    "episode": 139,
    "total_reward": 47.28140080745122,
    "episode_length": 512,
    "rlf_count": 0,
    "pp_count": 0,
    "ho_count": 0,
    "avg_reward_per_step": 0.09234648595205316,
    "entropy_coef": 0.03225714285714286,
    "ttt_final": 320,
    "hys_final": 3.5
  },
  {
    "episode": 140,
    "total_reward": 19.574403440092105,
    "episode_length": 512,
    "rlf_count": 0,
    "pp_count": 0,
    "ho_count": 4,
    "avg_reward_per_step": 0.03823125671892989,
    "entropy_coef": 0.03212857142857143,
    "ttt_final": 320,
    "hys_final": 5.0
  },
  {
    "episode": 141,
    "total_reward": 20.344233954491003,
    "episode_length": 512,
    "rlf_count": 0,
    "pp_count": 0,
    "ho_count": 0,
    "avg_reward_per_step": 0.03973483194236524,
    "entropy_coef": 0.032,
    "ttt_final": 240,
    "hys_final": 4.0
  },
  {
    "episode": 142,
    "total_reward": 42.4198531806037,
    "episode_length": 512,
    "rlf_count": 0,
    "pp_count": 0,
    "ho_count": 1,
    "avg_reward_per_step": 0.0828512757433666,
    "entropy_coef": 0.03187142857142857,
    "ttt_final": 100,
    "hys_final": 4.5
  },
  {
    "episode": 143,
    "total_reward": -39.315151045919634,
    "episode_length": 512,
    "rlf_count": 1,
    "pp_count": 3,
    "ho_count": 30,
    "avg_reward_per_step": -0.07678740438656179,
    "entropy_coef": 0.03174285714285714,
    "ttt_final": 320,
    "hys_final": 5.0
  },
  {
    "episode": 144,
    "total_reward": 25.845078590920906,
    "episode_length": 512,
    "rlf_count": 0,
    "pp_count": 0,
    "ho_count": 1,
    "avg_reward_per_step": 0.050478669122892394,
    "entropy_coef": 0.03161428571428571,
    "ttt_final": 200,
    "hys_final": 3.5
  },
  {
    "episode": 145,
    "total_reward": 37.22126514125346,
    "episode_length": 512,
    "rlf_count": 0,
    "pp_count": 0,
    "ho_count": 0,
    "avg_reward_per_step": 0.07269778347901067,
    "entropy_coef": 0.031485714285714284,
    "ttt_final": 320,
    "hys_final": 5.0
  },
  {
    "episode": 146,
    "total_reward": 27.546424163062152,
    "episode_length": 512,
    "rlf_count": 0,
    "pp_count": 0,
    "ho_count": 1,
    "avg_reward_per_step": 0.053801609693480766,
    "entropy_coef": 0.03135714285714286,
    "ttt_final": 160,
    "hys_final": 5.0
  },
  {
    "episode": 147,
    "total_reward": 30.756635966620284,
    "episode_length": 512,
    "rlf_count": 0,
    "pp_count": 0,
    "ho_count": 1,
    "avg_reward_per_step": 0.06007155462230524,
    "entropy_coef": 0.03122857142857143,
    "ttt_final": 160,
    "hys_final": 3.5
  },
  {
    "episode": 148,
    "total_reward": -7.942630046987849,
    "episode_length": 512,
    "rlf_count": 0,
    "pp_count": 0,
    "ho_count": 19,
    "avg_reward_per_step": -0.015512949310523142,
    "entropy_coef": 0.031100000000000003,
    "ttt_final": 240,
    "hys_final": 5.0
  },
  {
    "episode": 149,
    "total_reward": 28.56397846347661,
    "episode_length": 508,
    "rlf_count": 0,
    "pp_count": 0,
    "ho_count": 1,
    "avg_reward_per_step": 0.05622830406196183,
    "entropy_coef": 0.03097142857142857,
    "ttt_final": 320,
    "hys_final": 5.0
  },
  {
    "episode": 150,
    "total_reward": 8.89974609953866,
    "episode_length": 512,
    "rlf_count": 0,
    "pp_count": 1,
    "ho_count": 13,
    "avg_reward_per_step": 0.017382316600661446,
    "entropy_coef": 0.030842857142857144,
    "ttt_final": 200,
    "hys_final": 5.0
  },
  {
    "episode": 151,
    "total_reward": -3.151050363729209,
    "episode_length": 145,
    "rlf_count": 0,
    "pp_count": 0,
    "ho_count": 5,
    "avg_reward_per_step": -0.021731381818822133,
    "entropy_coef": 0.030714285714285715,
    "ttt_final": 100,
    "hys_final": 3.0
  },
  {
    "episode": 152,
    "total_reward": 24.357874856630616,
    "episode_length": 512,
    "rlf_count": 0,
    "pp_count": 0,
    "ho_count": 0,
    "avg_reward_per_step": 0.04757397432935667,
    "entropy_coef": 0.030585714285714286,
    "ttt_final": 160,
    "hys_final": 2.0
  },
  {
    "episode": 153,
    "total_reward": 24.258002044104778,
    "episode_length": 512,
    "rlf_count": 0,
    "pp_count": 0,
    "ho_count": 1,
    "avg_reward_per_step": 0.047378910242392144,
    "entropy_coef": 0.03045714285714286,
    "ttt_final": 320,
    "hys_final": 4.5
  },
  {
    "episode": 154,
    "total_reward": -6.339187171071347,
    "episode_length": 512,
    "rlf_count": 0,
    "pp_count": 1,
    "ho_count": 11,
    "avg_reward_per_step": -0.012381224943498725,
    "entropy_coef": 0.030328571428571427,
    "ttt_final": 320,
    "hys_final": 5.0
  },
  {
    "episode": 155,
    "total_reward": -14.649013933304174,
    "episode_length": 400,
    "rlf_count": 0,
    "pp_count": 0,
    "ho_count": 14,
    "avg_reward_per_step": -0.03662253483326043,
    "entropy_coef": 0.0302,
    "ttt_final": 320,
    "hys_final": 5.0
  },
  {
    "episode": 156,
    "total_reward": -12.807822120719484,
    "episode_length": 512,
    "rlf_count": 0,
    "pp_count": 1,
    "ho_count": 17,
    "avg_reward_per_step": -0.025015277579530242,
    "entropy_coef": 0.030071428571428572,
    "ttt_final": 240,
    "hys_final": 3.0
  },
  {
    "episode": 157,
    "total_reward": 35.913938697175915,
    "episode_length": 512,
    "rlf_count": 0,
    "pp_count": 0,
    "ho_count": 2,
    "avg_reward_per_step": 0.07014441151792171,
    "entropy_coef": 0.029942857142857143,
    "ttt_final": 240,
    "hys_final": 4.0
  },
  {
    "episode": 158,
    "total_reward": 31.82446552227175,
    "episode_length": 512,
    "rlf_count": 0,
    "pp_count": 0,
    "ho_count": 0,
    "avg_reward_per_step": 0.062157159223187014,
    "entropy_coef": 0.029814285714285713,
    "ttt_final": 320,
    "hys_final": 3.5
  },
  {
    "episode": 159,
    "total_reward": 11.641101786990973,
    "episode_length": 512,
    "rlf_count": 0,
    "pp_count": 0,
    "ho_count": 10,
    "avg_reward_per_step": 0.022736526927716744,
    "entropy_coef": 0.029685714285714287,
    "ttt_final": 320,
    "hys_final": 3.0
  },
  {
    "episode": 160,
    "total_reward": 37.91572799746269,
    "episode_length": 512,
    "rlf_count": 0,
    "pp_count": 0,
    "ho_count": 1,
    "avg_reward_per_step": 0.07405415624504431,
    "entropy_coef": 0.029557142857142858,
    "ttt_final": 320,
    "hys_final": 4.0
  },
  {
    "episode": 161,
    "total_reward": -1.2554739977555036,
    "episode_length": 512,
    "rlf_count": 0,
    "pp_count": 0,
    "ho_count": 9,
    "avg_reward_per_step": -0.002452097651866218,
    "entropy_coef": 0.02942857142857143,
    "ttt_final": 320,
    "hys_final": 4.5
  },
  {
    "episode": 162,
    "total_reward": 7.155304983776975,
    "episode_length": 512,
    "rlf_count": 2,
    "pp_count": 1,
    "ho_count": 13,
    "avg_reward_per_step": 0.013975205046439404,
    "entropy_coef": 0.0293,
    "ttt_final": 320,
    "hys_final": 2.5
  },
  {
    "episode": 163,
    "total_reward": 49.269331706296605,
    "episode_length": 512,
    "rlf_count": 0,
    "pp_count": 0,
    "ho_count": 0,
    "avg_reward_per_step": 0.09622916348886056,
    "entropy_coef": 0.02917142857142857,
    "ttt_final": 200,
    "hys_final": 2.0
  },
  {
    "episode": 164,
    "total_reward": 20.940885709877982,
    "episode_length": 512,
    "rlf_count": 0,
    "pp_count": 0,
    "ho_count": 1,
    "avg_reward_per_step": 0.04090016740210543,
    "entropy_coef": 0.029042857142857145,
    "ttt_final": 320,
    "hys_final": 4.5
  },
  {
    "episode": 165,
    "total_reward": 15.889529795354742,
    "episode_length": 512,
    "rlf_count": 0,
    "pp_count": 0,
    "ho_count": 6,
    "avg_reward_per_step": 0.03103423788155223,
    "entropy_coef": 0.028914285714285715,
    "ttt_final": 160,
    "hys_final": 5.0
  },
  {
    "episode": 166,
    "total_reward": 33.83564007273476,
    "episode_length": 512,
    "rlf_count": 0,
    "pp_count": 0,
    "ho_count": 0,
    "avg_reward_per_step": 0.06608523451706008,
    "entropy_coef": 0.028785714285714286,
    "ttt_final": 200,
    "hys_final": 4.0
  },
  {
    "episode": 167,
    "total_reward": 7.627509998593465,
    "episode_length": 120,
    "rlf_count": 0,
    "pp_count": 0,
    "ho_count": 0,
    "avg_reward_per_step": 0.0635625833216122,
    "entropy_coef": 0.028657142857142857,
    "ttt_final": 320,
    "hys_final": 2.5
  },
  {
    "episode": 168,
    "total_reward": 18.300038966965403,
    "episode_length": 512,
    "rlf_count": 0,
    "pp_count": 1,
    "ho_count": 7,
    "avg_reward_per_step": 0.0357422636073543,
    "entropy_coef": 0.028528571428571427,
    "ttt_final": 320,
    "hys_final": 4.5
  },
  {
    "episode": 169,
    "total_reward": -13.136096142596214,
    "episode_length": 512,
    "rlf_count": 0,
    "pp_count": 1,
    "ho_count": 17,
    "avg_reward_per_step": -0.02565643777850823,
    "entropy_coef": 0.0284,
    "ttt_final": 240,
    "hys_final": 2.0
  },
  {
    "episode": 170,
    "total_reward": -12.698609522224446,
    "episode_length": 512,
    "rlf_count": 0,
    "pp_count": 0,
    "ho_count": 16,
    "avg_reward_per_step": -0.02480197172309462,
    "entropy_coef": 0.028271428571428572,
    "ttt_final": 320,
    "hys_final": 5.0
  },
  {
    "episode": 171,
    "total_reward": 23.080731872031347,
    "episode_length": 512,
    "rlf_count": 0,
    "pp_count": 0,
    "ho_count": 3,
    "avg_reward_per_step": 0.045079554437561224,
    "entropy_coef": 0.028142857142857143,
    "ttt_final": 240,
    "hys_final": 3.0
  },
  {
    "episode": 172,
    "total_reward": 28.97500882575246,
    "episode_length": 512,
    "rlf_count": 0,
    "pp_count": 0,
    "ho_count": 1,
    "avg_reward_per_step": 0.056591814112797775,
    "entropy_coef": 0.028014285714285717,
    "ttt_final": 160,
    "hys_final": 2.0
  },
  {
    "episode": 173,
    "total_reward": -10.2919480615329,
    "episode_length": 512,
    "rlf_count": 0,
    "pp_count": 1,
    "ho_count": 10,
    "avg_reward_per_step": -0.020101461057681444,
    "entropy_coef": 0.027885714285714285,
    "ttt_final": 200,
    "hys_final": 2.5
  },
  {
    "episode": 174,
    "total_reward": 14.543404343416851,
    "episode_length": 350,
    "rlf_count": 0,
    "pp_count": 0,
    "ho_count": 2,
    "avg_reward_per_step": 0.04155258383833386,
    "entropy_coef": 0.02775714285714286,
    "ttt_final": 320,
    "hys_final": 4.0
  },
  {
    "episode": 175,
    "total_reward": 19.862958493049288,
    "episode_length": 512,
    "rlf_count": 0,
    "pp_count": 0,
    "ho_count": 1,
    "avg_reward_per_step": 0.03879484080673689,
    "entropy_coef": 0.02762857142857143,
    "ttt_final": 160,
    "hys_final": 2.0
  },
  {
    "episode": 176,
    "total_reward": 11.054852631892306,
    "episode_length": 512,
    "rlf_count": 0,
    "pp_count": 0,
    "ho_count": 7,
    "avg_reward_per_step": 0.02159150904666466,
    "entropy_coef": 0.0275,
    "ttt_final": 320,
    "hys_final": 3.5
  },
  {
    "episode": 177,
    "total_reward": -62.884953771994425,
    "episode_length": 512,
    "rlf_count": 15,
    "pp_count": 2,
    "ho_count": 13,
    "avg_reward_per_step": -0.12282217533592661,
    "entropy_coef": 0.02737142857142857,
    "ttt_final": 200,
    "hys_final": 4.5
  },
  {
    "episode": 178,
    "total_reward": 11.090295717321737,
    "episode_length": 512,
    "rlf_count": 0,
    "pp_count": 0,
    "ho_count": 7,
    "avg_reward_per_step": 0.02166073382289402,
    "entropy_coef": 0.027242857142857145,
    "ttt_final": 320,
    "hys_final": 2.0
  },
  {
    "episode": 179,
    "total_reward": 19.701963244060472,
    "episode_length": 512,
    "rlf_count": 0,
    "pp_count": 0,
    "ho_count": 1,
    "avg_reward_per_step": 0.03848039696105561,
    "entropy_coef": 0.027114285714285716,
    "ttt_final": 200,
    "hys_final": 2.5
  },
  {
    "episode": 180,
    "total_reward": 38.66654693184803,
    "episode_length": 512,
    "rlf_count": 0,
    "pp_count": 0,
    "ho_count": 1,
    "avg_reward_per_step": 0.07552059947626569,
    "entropy_coef": 0.026985714285714283,
    "ttt_final": 320,
    "hys_final": 5.0
  },
  {
    "episode": 181,
    "total_reward": 47.528877171006734,
    "episode_length": 512,
    "rlf_count": 0,
    "pp_count": 0,
    "ho_count": 0,
    "avg_reward_per_step": 0.09282983822462253,
    "entropy_coef": 0.02685714285714286,
    "ttt_final": 320,
    "hys_final": 2.5
  },
  {
    "episode": 182,
    "total_reward": 25.537379867273692,
    "episode_length": 512,
    "rlf_count": 0,
    "pp_count": 0,
    "ho_count": 5,
    "avg_reward_per_step": 0.04987769505326893,
    "entropy_coef": 0.026728571428571428,
    "ttt_final": 200,
    "hys_final": 2.5
  },
  {
    "episode": 183,
    "total_reward": 25.944697623683638,
    "episode_length": 512,
    "rlf_count": 0,
    "pp_count": 0,
    "ho_count": 3,
    "avg_reward_per_step": 0.050673237546257105,
    "entropy_coef": 0.0266,
    "ttt_final": 320,
    "hys_final": 3.5
  },
  {
    "episode": 184,
    "total_reward": 6.219115904654025,
    "episode_length": 512,
    "rlf_count": 0,
    "pp_count": 0,
    "ho_count": 1,
    "avg_reward_per_step": 0.012146710751277393,
    "entropy_coef": 0.02647142857142857,
    "ttt_final": 100,
    "hys_final": 2.5
  },
  {
    "episode": 185,
    "total_reward": 19.31448588639975,
    "episode_length": 512,
    "rlf_count": 0,
    "pp_count": 0,
    "ho_count": 1,
    "avg_reward_per_step": 0.037723605246874514,
    "entropy_coef": 0.026342857142857144,
    "ttt_final": 100,
    "hys_final": 2.0
  },
  {
    "episode": 186,
    "total_reward": 34.80254023119874,
    "episode_length": 512,
    "rlf_count": 0,
    "pp_count": 0,
    "ho_count": 0,
    "avg_reward_per_step": 0.06797371138906004,
    "entropy_coef": 0.026214285714285714,
    "ttt_final": 200,
    "hys_final": 2.5
  },
  {
    "episode": 187,
    "total_reward": 20.967377972642648,
    "episode_length": 512,
    "rlf_count": 0,
    "pp_count": 0,
    "ho_count": 2,
    "avg_reward_per_step": 0.04095191010281767,
    "entropy_coef": 0.026085714285714285,
    "ttt_final": 200,
    "hys_final": 3.0
  },
  {
    "episode": 188,
    "total_reward": 32.935528569792424,
    "episode_length": 512,
    "rlf_count": 0,
    "pp_count": 0,
    "ho_count": 2,
    "avg_reward_per_step": 0.06432720423787583,
    "entropy_coef": 0.02595714285714286,
    "ttt_final": 100,
    "hys_final": 4.5
  },
  {
    "episode": 189,
    "total_reward": 37.466428344356025,
    "episode_length": 512,
    "rlf_count": 0,
    "pp_count": 0,
    "ho_count": 0,
    "avg_reward_per_step": 0.07317661786007036,
    "entropy_coef": 0.02582857142857143,
    "ttt_final": 160,
    "hys_final": 2.5
  },
  {
    "episode": 190,
    "total_reward": 14.07371687349754,
    "episode_length": 512,
    "rlf_count": 0,
    "pp_count": 2,
    "ho_count": 8,
    "avg_reward_per_step": 0.027487728268549883,
    "entropy_coef": 0.025699999999999997,
    "ttt_final": 200,
    "hys_final": 3.0
  },
  {
    "episode": 191,
    "total_reward": -72.80998004778489,
    "episode_length": 512,
    "rlf_count": 17,
    "pp_count": 1,
    "ho_count": 17,
    "avg_reward_per_step": -0.14220699228082986,
    "entropy_coef": 0.025571428571428575,
    "ttt_final": 240,
    "hys_final": 2.0
  },
  {
    "episode": 192,
    "total_reward": 18.57901032078204,
    "episode_length": 512,
    "rlf_count": 0,
    "pp_count": 0,
    "ho_count": 4,
    "avg_reward_per_step": 0.03628712953277742,
    "entropy_coef": 0.025442857142857142,
    "ttt_final": 200,
    "hys_final": 2.0
  },
  {
    "episode": 193,
    "total_reward": 14.571588316312697,
    "episode_length": 512,
    "rlf_count": 0,
    "pp_count": 0,
    "ho_count": 1,
    "avg_reward_per_step": 0.028460133430298237,
    "entropy_coef": 0.025314285714285713,
    "ttt_final": 240,
    "hys_final": 2.0
  },
  {
    "episode": 194,
    "total_reward": 8.104600144786826,
    "episode_length": 512,
    "rlf_count": 0,
    "pp_count": 0,
    "ho_count": 1,
    "avg_reward_per_step": 0.01582929715778677,
    "entropy_coef": 0.025185714285714287,
    "ttt_final": 320,
    "hys_final": 2.0
  },
  {
    "episode": 195,
    "total_reward": -5.349825462565542,
    "episode_length": 512,
    "rlf_count": 0,
    "pp_count": 0,
    "ho_count": 3,
    "avg_reward_per_step": -0.010448877856573325,
    "entropy_coef": 0.025057142857142858,
    "ttt_final": 200,
    "hys_final": 2.0
  },
  {
    "episode": 196,
    "total_reward": 36.869931069060236,
    "episode_length": 512,
    "rlf_count": 0,
    "pp_count": 0,
    "ho_count": 1,
    "avg_reward_per_step": 0.07201158411925827,
    "entropy_coef": 0.02492857142857143,
    "ttt_final": 320,
    "hys_final": 2.0
  },
  {
    "episode": 197,
    "total_reward": 39.48543153229379,
    "episode_length": 512,
    "rlf_count": 0,
    "pp_count": 0,
    "ho_count": 2,
    "avg_reward_per_step": 0.0771199834615113,
    "entropy_coef": 0.0248,
    "ttt_final": 100,
    "hys_final": 2.0
  },
  {
    "episode": 198,
    "total_reward": 23.169734388390754,
    "episode_length": 512,
    "rlf_count": 0,
    "pp_count": 0,
    "ho_count": 4,
    "avg_reward_per_step": 0.04525338747732569,
    "entropy_coef": 0.024671428571428573,
    "ttt_final": 320,
    "hys_final": 2.0
  },
  {
    "episode": 199,
    "total_reward": -54.689920817354725,
    "episode_length": 512,
    "rlf_count": 0,
    "pp_count": 8,
    "ho_count": 33,
    "avg_reward_per_step": -0.10681625159639595,
    "entropy_coef": 0.02454285714285714,
    "ttt_final": 320,
    "hys_final": 3.0
  },
  {
    "episode": 200,
    "total_reward": -38.59202065800782,
    "episode_length": 512,
    "rlf_count": 0,
    "pp_count": 5,
    "ho_count": 24,
    "avg_reward_per_step": -0.07537504034767152,
    "entropy_coef": 0.02441428571428571,
    "ttt_final": 320,
    "hys_final": 2.0
  },
  {
    "episode": 201,
    "total_reward": 32.137541615416936,
    "episode_length": 512,
    "rlf_count": 0,
    "pp_count": 0,
    "ho_count": 3,
    "avg_reward_per_step": 0.0627686359676112,
    "entropy_coef": 0.024285714285714285,
    "ttt_final": 100,
    "hys_final": 2.0
  },
  {
    "episode": 202,
    "total_reward": 19.861129664554117,
    "episode_length": 512,
    "rlf_count": 0,
    "pp_count": 0,
    "ho_count": 2,
    "avg_reward_per_step": 0.03879126887608226,
    "entropy_coef": 0.024157142857142856,
    "ttt_final": 100,
    "hys_final": 2.0
  },
  {
    "episode": 203,
    "total_reward": 44.0673061859823,
    "episode_length": 512,
    "rlf_count": 0,
    "pp_count": 0,
    "ho_count": 2,
    "avg_reward_per_step": 0.08606895739449667,
    "entropy_coef": 0.024028571428571427,
    "ttt_final": 240,
    "hys_final": 2.0
  },
  {
    "episode": 204,
    "total_reward": 29.030606823190794,
    "episode_length": 512,
    "rlf_count": 0,
    "pp_count": 0,
    "ho_count": 0,
    "avg_reward_per_step": 0.05670040395154452,
    "entropy_coef": 0.0239,
    "ttt_final": 240,
    "hys_final": 2.0
  },
  {
    "episode": 205,
    "total_reward": 18.964556975605984,
    "episode_length": 512,
    "rlf_count": 0,
    "pp_count": 0,
    "ho_count": 3,
    "avg_reward_per_step": 0.03704015034298044,
    "entropy_coef": 0.023771428571428572,
    "ttt_final": 240,
    "hys_final": 2.0
  },
  {
    "episode": 206,
    "total_reward": 25.39677011280421,
    "episode_length": 512,
    "rlf_count": 0,
    "pp_count": 0,
    "ho_count": 0,
    "avg_reward_per_step": 0.04960306662657072,
    "entropy_coef": 0.023642857142857143,
    "ttt_final": 320,
    "hys_final": 2.0
  },
  {
    "episode": 207,
    "total_reward": -6.753058773333965,
    "episode_length": 512,
    "rlf_count": 0,
    "pp_count": 1,
    "ho_count": 5,
    "avg_reward_per_step": -0.0131895679166679,
    "entropy_coef": 0.023514285714285717,
    "ttt_final": 320,
    "hys_final": 3.0
  },
  {
    "episode": 208,
    "total_reward": 49.51121960403871,
    "episode_length": 512,
    "rlf_count": 0,
    "pp_count": 0,
    "ho_count": 0,
    "avg_reward_per_step": 0.0967016007891381,
    "entropy_coef": 0.023385714285714287,
    "ttt_final": 100,
    "hys_final": 2.0
  },
  {
    "episode": 209,
    "total_reward": 46.5319175528884,
    "episode_length": 512,
    "rlf_count": 0,
    "pp_count": 0,
    "ho_count": 0,
    "avg_reward_per_step": 0.09088265147048516,
    "entropy_coef": 0.023257142857142855,
    "ttt_final": 160,
    "hys_final": 2.0
  },
  {
    "episode": 210,
    "total_reward": -111.17947161711223,
    "episode_length": 512,
    "rlf_count": 26,
    "pp_count": 3,
    "ho_count": 19,
    "avg_reward_per_step": -0.21714740550217232,
    "entropy_coef": 0.023128571428571425,
    "ttt_final": 200,
    "hys_final": 3.5
  },
  {
    "episode": 211,
    "total_reward": 47.660670440767916,
    "episode_length": 512,
    "rlf_count": 0,
    "pp_count": 0,
    "ho_count": 0,
    "avg_reward_per_step": 0.09308724695462484,
    "entropy_coef": 0.023,
    "ttt_final": 100,
    "hys_final": 2.0
  },
  {
    "episode": 212,
    "total_reward": 28.556031281113576,
    "episode_length": 512,
    "rlf_count": 0,
    "pp_count": 0,
    "ho_count": 1,
    "avg_reward_per_step": 0.05577349859592495,
    "entropy_coef": 0.02287142857142857,
    "ttt_final": 100,
    "hys_final": 2.0
  },
  {
    "episode": 213,
    "total_reward": 15.543321421738797,
    "episode_length": 512,
    "rlf_count": 0,
    "pp_count": 0,
    "ho_count": 9,
    "avg_reward_per_step": 0.03035804965183359,
    "entropy_coef": 0.02274285714285714,
    "ttt_final": 100,
    "hys_final": 2.0
  },
  {
    "episode": 214,
    "total_reward": -73.0852096015164,
    "episode_length": 512,
    "rlf_count": 0,
    "pp_count": 12,
    "ho_count": 47,
    "avg_reward_per_step": -0.1427445500029617,
    "entropy_coef": 0.022614285714285715,
    "ttt_final": 240,
    "hys_final": 2.0
  },
  {
    "episode": 215,
    "total_reward": 46.17005920719239,
    "episode_length": 512,
    "rlf_count": 0,
    "pp_count": 0,
    "ho_count": 0,
    "avg_reward_per_step": 0.09017589688904763,
    "entropy_coef": 0.022485714285714286,
    "ttt_final": 100,
    "hys_final": 2.0
  },
  {
    "episode": 216,
    "total_reward": 38.94807252894715,
    "episode_length": 512,
    "rlf_count": 0,
    "pp_count": 0,
    "ho_count": 1,
    "avg_reward_per_step": 0.0760704541580999,
    "entropy_coef": 0.022357142857142857,
    "ttt_final": 200,
    "hys_final": 2.0
  },
  {
    "episode": 217,
    "total_reward": 34.17724687007385,
    "episode_length": 512,
    "rlf_count": 0,
    "pp_count": 0,
    "ho_count": 2,
    "avg_reward_per_step": 0.06675243529311299,
    "entropy_coef": 0.02222857142857143,
    "ttt_final": 320,
    "hys_final": 2.0
  },
  {
    "episode": 218,
    "total_reward": 44.4706017840222,
    "episode_length": 512,
    "rlf_count": 0,
    "pp_count": 0,
    "ho_count": 0,
    "avg_reward_per_step": 0.08685664410941836,
    "entropy_coef": 0.022099999999999998,
    "ttt_final": 100,
    "hys_final": 2.0
  },
  {
    "episode": 219,
    "total_reward": 35.3138773469837,
    "episode_length": 512,
    "rlf_count": 0,
    "pp_count": 0,
    "ho_count": 3,
    "avg_reward_per_step": 0.06897241669332754,
    "entropy_coef": 0.02197142857142857,
    "ttt_final": 100,
    "hys_final": 2.0
  },
  {
    "episode": 220,
    "total_reward": 20.245998212169983,
    "episode_length": 249,
    "rlf_count": 0,
    "pp_count": 0,
    "ho_count": 0,
    "avg_reward_per_step": 0.08130922976775094,
    "entropy_coef": 0.021842857142857143,
    "ttt_final": 100,
    "hys_final": 2.5
  },
  {
    "episode": 221,
    "total_reward": 11.24740011252641,
    "episode_length": 108,
    "rlf_count": 0,
    "pp_count": 0,
    "ho_count": 0,
    "avg_reward_per_step": 0.1041425936345038,
    "entropy_coef": 0.021714285714285714,
    "ttt_final": 160,
    "hys_final": 2.0
  },
  {
    "episode": 222,
    "total_reward": -1.7321190978768155,
    "episode_length": 512,
    "rlf_count": 0,
    "pp_count": 1,
    "ho_count": 4,
    "avg_reward_per_step": -0.0033830451130406553,
    "entropy_coef": 0.021585714285714284,
    "ttt_final": 200,
    "hys_final": 2.0
  },
  {
    "episode": 223,
    "total_reward": 11.84359949411155,
    "episode_length": 219,
    "rlf_count": 0,
    "pp_count": 0,
    "ho_count": 0,
    "avg_reward_per_step": 0.05408036298681073,
    "entropy_coef": 0.02145714285714286,
    "ttt_final": 160,
    "hys_final": 2.0
  },
  {
    "episode": 224,
    "total_reward": 33.08451983297996,
    "episode_length": 512,
    "rlf_count": 0,
    "pp_count": 0,
    "ho_count": 1,
    "avg_reward_per_step": 0.06461820279878898,
    "entropy_coef": 0.02132857142857143,
    "ttt_final": 160,
    "hys_final": 2.5
  },
  {
    "episode": 225,
    "total_reward": 8.591344517536987,
    "episode_length": 512,
    "rlf_count": 0,
    "pp_count": 0,
    "ho_count": 1,
    "avg_reward_per_step": 0.016779969760814428,
    "entropy_coef": 0.0212,
    "ttt_final": 320,
    "hys_final": 5.0
  },
  {
    "episode": 226,
    "total_reward": 5.797267498941388,
    "episode_length": 512,
    "rlf_count": 0,
    "pp_count": 0,
    "ho_count": 4,
    "avg_reward_per_step": 0.0113227880838699,
    "entropy_coef": 0.021071428571428567,
    "ttt_final": 160,
    "hys_final": 2.0
  },
  {
    "episode": 227,
    "total_reward": 23.038561438656465,
    "episode_length": 512,
    "rlf_count": 0,
    "pp_count": 0,
    "ho_count": 4,
    "avg_reward_per_step": 0.04499719030987591,
    "entropy_coef": 0.020942857142857145,
    "ttt_final": 100,
    "hys_final": 2.0
  },
  {
    "episode": 228,
    "total_reward": 22.897224128606148,
    "episode_length": 512,
    "rlf_count": 0,
    "pp_count": 0,
    "ho_count": 2,
    "avg_reward_per_step": 0.04472114087618388,
    "entropy_coef": 0.020814285714285712,
    "ttt_final": 320,
    "hys_final": 2.0
  },
  {
    "episode": 229,
    "total_reward": -2.1070043784387384,
    "episode_length": 512,
    "rlf_count": 0,
    "pp_count": 2,
    "ho_count": 11,
    "avg_reward_per_step": -0.004115242926638161,
    "entropy_coef": 0.020685714285714283,
    "ttt_final": 240,
    "hys_final": 2.0
  },
  {
    "episode": 230,
    "total_reward": 27.79028897153234,
    "episode_length": 512,
    "rlf_count": 0,
    "pp_count": 0,
    "ho_count": 3,
    "avg_reward_per_step": 0.054277908147524104,
    "entropy_coef": 0.020557142857142857,
    "ttt_final": 200,
    "hys_final": 2.0
  },
  {
    "episode": 231,
    "total_reward": 47.33001208572269,
    "episode_length": 512,
    "rlf_count": 0,
    "pp_count": 0,
    "ho_count": 0,
    "avg_reward_per_step": 0.09244142985492713,
    "entropy_coef": 0.020428571428571428,
    "ttt_final": 200,
    "hys_final": 2.0
  },
  {
    "episode": 232,
    "total_reward": -17.302993157131137,
    "episode_length": 512,
    "rlf_count": 0,
    "pp_count": 1,
    "ho_count": 12,
    "avg_reward_per_step": -0.03379490851002175,
    "entropy_coef": 0.0203,
    "ttt_final": 320,
    "hys_final": 3.5
  },
  {
    "episode": 233,
    "total_reward": 38.877617541035214,
    "episode_length": 512,
    "rlf_count": 0,
    "pp_count": 0,
    "ho_count": 2,
    "avg_reward_per_step": 0.0759328467598344,
    "entropy_coef": 0.020171428571428573,
    "ttt_final": 320,
    "hys_final": 3.0
  },
  {
    "episode": 234,
    "total_reward": 15.362934821468464,
    "episode_length": 512,
    "rlf_count": 0,
    "pp_count": 0,
    "ho_count": 3,
    "avg_reward_per_step": 0.030005732073180594,
    "entropy_coef": 0.020042857142857144,
    "ttt_final": 320,
    "hys_final": 2.0
  },
  {
    "episode": 235,
    "total_reward": 29.899735297862083,
    "episode_length": 512,
    "rlf_count": 0,
    "pp_count": 0,
    "ho_count": 1,
    "avg_reward_per_step": 0.05839792050363688,
    "entropy_coef": 0.019914285714285714,
    "ttt_final": 320,
    "hys_final": 2.0
  },
  {
    "episode": 236,
    "total_reward": -58.44257617163976,
    "episode_length": 512,
    "rlf_count": 0,
    "pp_count": 6,
    "ho_count": 41,
    "avg_reward_per_step": -0.1141456565852339,
    "entropy_coef": 0.01978571428571429,
    "ttt_final": 320,
    "hys_final": 3.0
  },
  {
    "episode": 237,
    "total_reward": 9.486279145718047,
    "episode_length": 512,
    "rlf_count": 0,
    "pp_count": 2,
    "ho_count": 8,
    "avg_reward_per_step": 0.01852788895648056,
    "entropy_coef": 0.019657142857142856,
    "ttt_final": 320,
    "hys_final": 2.5
  },
  {
    "episode": 238,
    "total_reward": 0.11275961210741102,
    "episode_length": 263,
    "rlf_count": 0,
    "pp_count": 0,
    "ho_count": 3,
    "avg_reward_per_step": 0.00042874377227152476,
    "entropy_coef": 0.019528571428571426,
    "ttt_final": 240,
    "hys_final": 2.0
  },
  {
    "episode": 239,
    "total_reward": -20.579342866777388,
    "episode_length": 512,
    "rlf_count": 0,
    "pp_count": 1,
    "ho_count": 18,
    "avg_reward_per_step": -0.040194029036674586,
    "entropy_coef": 0.019399999999999997,
    "ttt_final": 240,
    "hys_final": 2.5
  },
  {
    "episode": 240,
    "total_reward": 38.623204220081355,
    "episode_length": 512,
    "rlf_count": 0,
    "pp_count": 0,
    "ho_count": 2,
    "avg_reward_per_step": 0.0754359457423464,
    "entropy_coef": 0.01927142857142857,
    "ttt_final": 320,
    "hys_final": 2.0
  },
  {
    "episode": 241,
    "total_reward": 3.470121941045847,
    "episode_length": 512,
    "rlf_count": 0,
    "pp_count": 1,
    "ho_count": 7,
    "avg_reward_per_step": 0.0067775819161051696,
    "entropy_coef": 0.019142857142857142,
    "ttt_final": 320,
    "hys_final": 2.0
  },
  {
    "episode": 242,
    "total_reward": 38.03628384445032,
    "episode_length": 512,
    "rlf_count": 0,
    "pp_count": 0,
    "ho_count": 1,
    "avg_reward_per_step": 0.07428961688369203,
    "entropy_coef": 0.019014285714285713,
    "ttt_final": 320,
    "hys_final": 2.0
  },
  {
    "episode": 243,
    "total_reward": 20.56075601797379,
    "episode_length": 512,
    "rlf_count": 0,
    "pp_count": 0,
    "ho_count": 1,
    "avg_reward_per_step": 0.04015772659760506,
    "entropy_coef": 0.018885714285714287,
    "ttt_final": 240,
    "hys_final": 2.5
  },
  {
    "episode": 244,
    "total_reward": 43.97321977428973,
    "episode_length": 512,
    "rlf_count": 0,
    "pp_count": 0,
    "ho_count": 0,
    "avg_reward_per_step": 0.08588519487165963,
    "entropy_coef": 0.018757142857142858,
    "ttt_final": 320,
    "hys_final": 2.0
  },
  {
    "episode": 245,
    "total_reward": 34.23521713880007,
    "episode_length": 512,
    "rlf_count": 0,
    "pp_count": 0,
    "ho_count": 1,
    "avg_reward_per_step": 0.06686565847421888,
    "entropy_coef": 0.018628571428571425,
    "ttt_final": 200,
    "hys_final": 2.0
  },
  {
    "episode": 246,
    "total_reward": 8.102498739374159,
    "episode_length": 352,
    "rlf_count": 0,
    "pp_count": 0,
    "ho_count": 5,
    "avg_reward_per_step": 0.023018462327767497,
    "entropy_coef": 0.018500000000000003,
    "ttt_final": 240,
    "hys_final": 2.5
  },
  {
    "episode": 247,
    "total_reward": 19.03651991742945,
    "episode_length": 512,
    "rlf_count": 0,
    "pp_count": 0,
    "ho_count": 2,
    "avg_reward_per_step": 0.0371807029637294,
    "entropy_coef": 0.018371428571428573,
    "ttt_final": 320,
    "hys_final": 2.0
  },
  {
    "episode": 248,
    "total_reward": 23.333916394691542,
    "episode_length": 512,
    "rlf_count": 0,
    "pp_count": 0,
    "ho_count": 0,
    "avg_reward_per_step": 0.04557405545838192,
    "entropy_coef": 0.018242857142857144,
    "ttt_final": 320,
    "hys_final": 2.0
  },
  {
    "episode": 249,
    "total_reward": 28.078445186960092,
    "episode_length": 512,
    "rlf_count": 0,
    "pp_count": 0,
    "ho_count": 1,
    "avg_reward_per_step": 0.05484071325578143,
    "entropy_coef": 0.018114285714285715,
    "ttt_final": 320,
    "hys_final": 2.5
  },
  {
    "episode": 250,
    "total_reward": 14.574603848505317,
    "episode_length": 512,
    "rlf_count": 0,
    "pp_count": 0,
    "ho_count": 4,
    "avg_reward_per_step": 0.028466023141611948,
    "entropy_coef": 0.017985714285714285,
    "ttt_final": 320,
    "hys_final": 2.0
  },
  {
    "episode": 251,
    "total_reward": 10.345684626691833,
    "episode_length": 512,
    "rlf_count": 0,
    "pp_count": 0,
    "ho_count": 2,
    "avg_reward_per_step": 0.020206415286507486,
    "entropy_coef": 0.017857142857142856,
    "ttt_final": 320,
    "hys_final": 2.0
  },
  {
    "episode": 252,
    "total_reward": 41.66483564396662,
    "episode_length": 512,
    "rlf_count": 0,
    "pp_count": 0,
    "ho_count": 0,
    "avg_reward_per_step": 0.0813766321171223,
    "entropy_coef": 0.017728571428571427,
    "ttt_final": 320,
    "hys_final": 2.0
  },
  {
    "episode": 253,
    "total_reward": -8.826159828466519,
    "episode_length": 512,
    "rlf_count": 0,
    "pp_count": 4,
    "ho_count": 9,
    "avg_reward_per_step": -0.01723859341497367,
    "entropy_coef": 0.017599999999999998,
    "ttt_final": 320,
    "hys_final": 2.0
  },
  {
    "episode": 254,
    "total_reward": 15.770335031066764,
    "episode_length": 512,
    "rlf_count": 0,
    "pp_count": 0,
    "ho_count": 7,
    "avg_reward_per_step": 0.030801435607552274,
    "entropy_coef": 0.01747142857142857,
    "ttt_final": 320,
    "hys_final": 3.5
  },
  {
    "episode": 255,
    "total_reward": 7.572951678528703,
    "episode_length": 512,
    "rlf_count": 0,
    "pp_count": 0,
    "ho_count": 5,
    "avg_reward_per_step": 0.014790921247126373,
    "entropy_coef": 0.01734285714285714,
    "ttt_final": 320,
    "hys_final": 2.5
  },
  {
    "episode": 256,
    "total_reward": 31.88939687797023,
    "episode_length": 512,
    "rlf_count": 0,
    "pp_count": 0,
    "ho_count": 1,
    "avg_reward_per_step": 0.06228397827728561,
    "entropy_coef": 0.017214285714285717,
    "ttt_final": 240,
    "hys_final": 2.0
  },
  {
    "episode": 257,
    "total_reward": 47.665527913599576,
    "episode_length": 512,
    "rlf_count": 0,
    "pp_count": 0,
    "ho_count": 0,
    "avg_reward_per_step": 0.09309673420624917,
    "entropy_coef": 0.017085714285714287,
    "ttt_final": 160,
    "hys_final": 2.0
  },
  {
    "episode": 258,
    "total_reward": 20.651478935596263,
    "episode_length": 512,
    "rlf_count": 0,
    "pp_count": 0,
    "ho_count": 0,
    "avg_reward_per_step": 0.04033491979608645,
    "entropy_coef": 0.01695714285714285,
    "ttt_final": 240,
    "hys_final": 2.0
  },
  {
    "episode": 259,
    "total_reward": -2.541420639728837,
    "episode_length": 512,
    "rlf_count": 0,
    "pp_count": 1,
    "ho_count": 11,
    "avg_reward_per_step": -0.004963712186970385,
    "entropy_coef": 0.01682857142857143,
    "ttt_final": 320,
    "hys_final": 2.0
  },
  {
    "episode": 260,
    "total_reward": 25.934800727317995,
    "episode_length": 512,
    "rlf_count": 0,
    "pp_count": 0,
    "ho_count": 2,
    "avg_reward_per_step": 0.05065390767054296,
    "entropy_coef": 0.0167,
    "ttt_final": 240,
    "hys_final": 2.0
  },
  {
    "episode": 261,
    "total_reward": -18.366058316534673,
    "episode_length": 512,
    "rlf_count": 0,
    "pp_count": 3,
    "ho_count": 17,
    "avg_reward_per_step": -0.03587120764948178,
    "entropy_coef": 0.01657142857142857,
    "ttt_final": 320,
    "hys_final": 2.0
  },
  {
    "episode": 262,
    "total_reward": 25.270775164798437,
    "episode_length": 512,
    "rlf_count": 0,
    "pp_count": 0,
    "ho_count": 1,
    "avg_reward_per_step": 0.04935698274374695,
    "entropy_coef": 0.01644285714285714,
    "ttt_final": 320,
    "hys_final": 2.0
  },
  {
    "episode": 263,
    "total_reward": 30.721577069804543,
    "episode_length": 512,
    "rlf_count": 0,
    "pp_count": 0,
    "ho_count": 1,
    "avg_reward_per_step": 0.060003080214462,
    "entropy_coef": 0.01631428571428571,
    "ttt_final": 320,
    "hys_final": 2.5
  },
  {
    "episode": 264,
    "total_reward": -108.572195977389,
    "episode_length": 512,
    "rlf_count": 24,
    "pp_count": 3,
    "ho_count": 23,
    "avg_reward_per_step": -0.2120550702683379,
    "entropy_coef": 0.016185714285714282,
    "ttt_final": 320,
    "hys_final": 2.0
  },
  {
    "episode": 265,
    "total_reward": 0.0772025469403522,
    "episode_length": 512,
    "rlf_count": 0,
    "pp_count": 0,
    "ho_count": 12,
    "avg_reward_per_step": 0.00015078622449287538,
    "entropy_coef": 0.016057142857142853,
    "ttt_final": 320,
    "hys_final": 2.0
  },
  {
    "episode": 266,
    "total_reward": 40.773169611137696,
    "episode_length": 512,
    "rlf_count": 0,
    "pp_count": 0,
    "ho_count": 0,
    "avg_reward_per_step": 0.07963509689675331,
    "entropy_coef": 0.01592857142857143,
    "ttt_final": 320,
    "hys_final": 2.0
  },
  {
    "episode": 267,
    "total_reward": 28.10149932125079,
    "episode_length": 512,
    "rlf_count": 0,
    "pp_count": 0,
    "ho_count": 1,
    "avg_reward_per_step": 0.05488574086181795,
    "entropy_coef": 0.0158,
    "ttt_final": 320,
    "hys_final": 3.0
  },
  {
    "episode": 268,
    "total_reward": -12.155074133326691,
    "episode_length": 512,
    "rlf_count": 0,
    "pp_count": 2,
    "ho_count": 19,
    "avg_reward_per_step": -0.023740379166653693,
    "entropy_coef": 0.015671428571428565,
    "ttt_final": 320,
    "hys_final": 2.0
  },
  {
    "episode": 269,
    "total_reward": -69.59284958052774,
    "episode_length": 512,
    "rlf_count": 11,
    "pp_count": 1,
    "ho_count": 20,
    "avg_reward_per_step": -0.13592353433696824,
    "entropy_coef": 0.015542857142857143,
    "ttt_final": 320,
    "hys_final": 2.0
  },
  {
    "episode": 270,
    "total_reward": 15.397369566834747,
    "episode_length": 512,
    "rlf_count": 0,
    "pp_count": 0,
    "ho_count": 3,
    "avg_reward_per_step": 0.030072987435224116,
    "entropy_coef": 0.015414285714285714,
    "ttt_final": 320,
    "hys_final": 2.0
  },
  {
    "episode": 271,
    "total_reward": -7.0731744397204555,
    "episode_length": 184,
    "rlf_count": 0,
    "pp_count": 0,
    "ho_count": 4,
    "avg_reward_per_step": -0.03844116543326335,
    "entropy_coef": 0.015285714285714284,
    "ttt_final": 320,
    "hys_final": 2.0
  },
  {
    "episode": 272,
    "total_reward": -10.727766573074467,
    "episode_length": 499,
    "rlf_count": 0,
    "pp_count": 2,
    "ho_count": 13,
    "avg_reward_per_step": -0.021498530206562057,
    "entropy_coef": 0.015157142857142855,
    "ttt_final": 200,
    "hys_final": 2.0
  },
  {
    "episode": 273,
    "total_reward": 22.47327106852739,
    "episode_length": 512,
    "rlf_count": 0,
    "pp_count": 0,
    "ho_count": 1,
    "avg_reward_per_step": 0.043893107555717556,
    "entropy_coef": 0.015028571428571426,
    "ttt_final": 320,
    "hys_final": 2.5
  },
  {
    "episode": 274,
    "total_reward": -6.956080606686648,
    "episode_length": 512,
    "rlf_count": 0,
    "pp_count": 2,
    "ho_count": 13,
    "avg_reward_per_step": -0.013586094934934859,
    "entropy_coef": 0.014899999999999997,
    "ttt_final": 320,
    "hys_final": 2.0
  },
  {
    "episode": 275,
    "total_reward": 0.6131645166851634,
    "episode_length": 255,
    "rlf_count": 0,
    "pp_count": 0,
    "ho_count": 3,
    "avg_reward_per_step": 0.0024045667320986798,
    "entropy_coef": 0.014771428571428574,
    "ttt_final": 320,
    "hys_final": 2.0
  },
  {
    "episode": 276,
    "total_reward": 7.440388935729292,
    "episode_length": 512,
    "rlf_count": 0,
    "pp_count": 0,
    "ho_count": 7,
    "avg_reward_per_step": 0.014532009640096273,
    "entropy_coef": 0.014642857142857145,
    "ttt_final": 200,
    "hys_final": 2.0
  },
  {
    "episode": 277,
    "total_reward": -3.66556474694585,
    "episode_length": 512,
    "rlf_count": 0,
    "pp_count": 0,
    "ho_count": 0,
    "avg_reward_per_step": -0.007159306146378613,
    "entropy_coef": 0.014514285714285709,
    "ttt_final": 200,
    "hys_final": 2.0
  },
  {
    "episode": 278,
    "total_reward": 38.02538289852789,
    "episode_length": 512,
    "rlf_count": 0,
    "pp_count": 0,
    "ho_count": 2,
    "avg_reward_per_step": 0.07426832597368728,
    "entropy_coef": 0.01438571428571428,
    "ttt_final": 320,
    "hys_final": 2.0
  },
  {
    "episode": 279,
    "total_reward": 36.30135249982653,
    "episode_length": 512,
    "rlf_count": 0,
    "pp_count": 0,
    "ho_count": 2,
    "avg_reward_per_step": 0.07090107910122369,
    "entropy_coef": 0.014257142857142857,
    "ttt_final": 320,
    "hys_final": 2.0
  },
  {
    "episode": 280,
    "total_reward": 32.36306245736508,
    "episode_length": 512,
    "rlf_count": 0,
    "pp_count": 0,
    "ho_count": 1,
    "avg_reward_per_step": 0.06320910636204118,
    "entropy_coef": 0.014128571428571428,
    "ttt_final": 320,
    "hys_final": 2.0
  },
  {
    "episode": 281,
    "total_reward": -11.954779711019874,
    "episode_length": 512,
    "rlf_count": 0,
    "pp_count": 2,
    "ho_count": 18,
    "avg_reward_per_step": -0.023349179123085692,
    "entropy_coef": 0.013999999999999999,
    "ttt_final": 320,
    "hys_final": 2.0
  },
  {
    "episode": 282,
    "total_reward": -39.3713027428426,
    "episode_length": 512,
    "rlf_count": 0,
    "pp_count": 3,
    "ho_count": 27,
    "avg_reward_per_step": -0.07689707566961446,
    "entropy_coef": 0.01387142857142857,
    "ttt_final": 320,
    "hys_final": 2.0
  },
  {
    "episode": 283,
    "total_reward": 4.973734345193977,
    "episode_length": 512,
    "rlf_count": 0,
    "pp_count": 0,
    "ho_count": 11,
    "avg_reward_per_step": 0.009714324892956986,
    "entropy_coef": 0.01374285714285714,
    "ttt_final": 200,
    "hys_final": 2.0
  },
  {
    "episode": 284,
    "total_reward": 44.07351604867944,
    "episode_length": 512,
    "rlf_count": 0,
    "pp_count": 0,
    "ho_count": 0,
    "avg_reward_per_step": 0.08608108603257703,
    "entropy_coef": 0.01361428571428571,
    "ttt_final": 320,
    "hys_final": 2.0
  },
  {
    "episode": 285,
    "total_reward": 40.30267230639727,
    "episode_length": 512,
    "rlf_count": 0,
    "pp_count": 0,
    "ho_count": 0,
    "avg_reward_per_step": 0.07871615684843217,
    "entropy_coef": 0.013485714285714288,
    "ttt_final": 320,
    "hys_final": 2.0
  },
  {
    "episode": 286,
    "total_reward": 43.561613039347236,
    "episode_length": 512,
    "rlf_count": 0,
    "pp_count": 0,
    "ho_count": 0,
    "avg_reward_per_step": 0.08508127546747507,
    "entropy_coef": 0.013357142857142859,
    "ttt_final": 160,
    "hys_final": 2.0
  },
  {
    "episode": 287,
    "total_reward": -66.67286698564409,
    "episode_length": 512,
    "rlf_count": 0,
    "pp_count": 4,
    "ho_count": 42,
    "avg_reward_per_step": -0.13022044333133612,
    "entropy_coef": 0.013228571428571423,
    "ttt_final": 240,
    "hys_final": 2.0
  },
  {
    "episode": 288,
    "total_reward": -16.077441276876602,
    "episode_length": 512,
    "rlf_count": 0,
    "pp_count": 1,
    "ho_count": 21,
    "avg_reward_per_step": -0.03140125249389961,
    "entropy_coef": 0.0131,
    "ttt_final": 320,
    "hys_final": 2.0
  },
  {
    "episode": 289,
    "total_reward": -2.375222895549695,
    "episode_length": 512,
    "rlf_count": 0,
    "pp_count": 1,
    "ho_count": 9,
    "avg_reward_per_step": -0.004639107217870498,
    "entropy_coef": 0.012971428571428571,
    "ttt_final": 200,
    "hys_final": 2.0
  },
  {
    "episode": 290,
    "total_reward": 39.940813165165984,
    "episode_length": 512,
    "rlf_count": 0,
    "pp_count": 0,
    "ho_count": 1,
    "avg_reward_per_step": 0.07800940071321481,
    "entropy_coef": 0.012842857142857142,
    "ttt_final": 100,
    "hys_final": 2.0
  },
  {
    "episode": 291,
    "total_reward": 37.020262421734934,
    "episode_length": 512,
    "rlf_count": 0,
    "pp_count": 0,
    "ho_count": 1,
    "avg_reward_per_step": 0.07230520004245104,
    "entropy_coef": 0.012714285714285713,
    "ttt_final": 160,
    "hys_final": 2.0
  },
  {
    "episode": 292,
    "total_reward": -18.220291746133977,
    "episode_length": 512,
    "rlf_count": 0,
    "pp_count": 1,
    "ho_count": 14,
    "avg_reward_per_step": -0.035586507316667924,
    "entropy_coef": 0.012585714285714283,
    "ttt_final": 320,
    "hys_final": 2.0
  },
  {
    "episode": 293,
    "total_reward": -4.797304761948013,
    "episode_length": 512,
    "rlf_count": 0,
    "pp_count": 1,
    "ho_count": 7,
    "avg_reward_per_step": -0.009369735863179712,
    "entropy_coef": 0.012457142857142854,
    "ttt_final": 320,
    "hys_final": 2.0
  },
  {
    "episode": 294,
    "total_reward": 21.668470636729353,
    "episode_length": 512,
    "rlf_count": 0,
    "pp_count": 0,
    "ho_count": 5,
    "avg_reward_per_step": 0.04232123171236202,
    "entropy_coef": 0.012328571428571425,
    "ttt_final": 320,
    "hys_final": 2.0
  },
  {
    "episode": 295,
    "total_reward": 42.148722720539176,
    "episode_length": 512,
    "rlf_count": 0,
    "pp_count": 0,
    "ho_count": 0,
    "avg_reward_per_step": 0.08232172406355308,
    "entropy_coef": 0.012200000000000003,
    "ttt_final": 240,
    "hys_final": 2.0
  },
  {
    "episode": 296,
    "total_reward": -101.26646641570242,
    "episode_length": 512,
    "rlf_count": 24,
    "pp_count": 1,
    "ho_count": 18,
    "avg_reward_per_step": -0.1977860672181688,
    "entropy_coef": 0.012071428571428566,
    "ttt_final": 240,
    "hys_final": 2.0
  },
  {
    "episode": 297,
    "total_reward": 13.487724471680732,
    "episode_length": 512,
    "rlf_count": 0,
    "pp_count": 0,
    "ho_count": 3,
    "avg_reward_per_step": 0.02634321185875143,
    "entropy_coef": 0.011942857142857137,
    "ttt_final": 320,
    "hys_final": 2.0
  },
  {
    "episode": 298,
    "total_reward": 14.703683918183273,
    "episode_length": 512,
    "rlf_count": 0,
    "pp_count": 1,
    "ho_count": 4,
    "avg_reward_per_step": 0.028718132652701706,
    "entropy_coef": 0.011814285714285715,
    "ttt_final": 320,
    "hys_final": 2.0
  },
  {
    "episode": 299,
    "total_reward": -31.28792811879653,
    "episode_length": 512,
    "rlf_count": 0,
    "pp_count": 1,
    "ho_count": 16,
    "avg_reward_per_step": -0.06110923460702447,
    "entropy_coef": 0.011685714285714285,
    "ttt_final": 320,
    "hys_final": 2.0
  },
  {
    "episode": 300,
    "total_reward": -21.67577418548258,
    "episode_length": 512,
    "rlf_count": 0,
    "pp_count": 1,
    "ho_count": 21,
    "avg_reward_per_step": -0.042335496456020666,
    "entropy_coef": 0.011557142857142856,
    "ttt_final": 200,
    "hys_final": 2.0
  },
  {
    "episode": 301,
    "total_reward": 18.706974208202322,
    "episode_length": 512,
    "rlf_count": 0,
    "pp_count": 0,
    "ho_count": 5,
    "avg_reward_per_step": 0.03653705900039516,
    "entropy_coef": 0.011428571428571427,
    "ttt_final": 240,
    "hys_final": 2.5
  },
  {
    "episode": 302,
    "total_reward": 23.25821697853656,
    "episode_length": 512,
    "rlf_count": 0,
    "pp_count": 0,
    "ho_count": 6,
    "avg_reward_per_step": 0.04542620503620422,
    "entropy_coef": 0.011299999999999998,
    "ttt_final": 320,
    "hys_final": 2.0
  },
  {
    "episode": 303,
    "total_reward": -0.9562824101798908,
    "episode_length": 512,
    "rlf_count": 0,
    "pp_count": 2,
    "ho_count": 13,
    "avg_reward_per_step": -0.0018677390823825992,
    "entropy_coef": 0.011171428571428568,
    "ttt_final": 320,
    "hys_final": 2.0
  },
  {
    "episode": 304,
    "total_reward": 48.60528312384614,
    "episode_length": 512,
    "rlf_count": 0,
    "pp_count": 0,
    "ho_count": 0,
    "avg_reward_per_step": 0.094932193601262,
    "entropy_coef": 0.011042857142857139,
    "ttt_final": 160,
    "hys_final": 2.0
  },
  {
    "episode": 305,
    "total_reward": -58.39196203902488,
    "episode_length": 512,
    "rlf_count": 20,
    "pp_count": 1,
    "ho_count": 13,
    "avg_reward_per_step": -0.11404680085747047,
    "entropy_coef": 0.010914285714285717,
    "ttt_final": 320,
    "hys_final": 2.0
  },
  {
    "episode": 306,
    "total_reward": -32.68747877324501,
    "episode_length": 512,
    "rlf_count": 0,
    "pp_count": 1,
    "ho_count": 25,
    "avg_reward_per_step": -0.06384273197899416,
    "entropy_coef": 0.01078571428571428,
    "ttt_final": 320,
    "hys_final": 3.5
  },
  {
    "episode": 307,
    "total_reward": -35.27078293734368,
    "episode_length": 512,
    "rlf_count": 0,
    "pp_count": 3,
    "ho_count": 23,
    "avg_reward_per_step": -0.06888824792449938,
    "entropy_coef": 0.010657142857142851,
    "ttt_final": 320,
    "hys_final": 2.0
  },
  {
    "episode": 308,
    "total_reward": 28.591920632443514,
    "episode_length": 512,
    "rlf_count": 0,
    "pp_count": 0,
    "ho_count": 4,
    "avg_reward_per_step": 0.05584359498524124,
    "entropy_coef": 0.010528571428571429,
    "ttt_final": 240,
    "hys_final": 2.0
  },
  {
    "episode": 309,
    "total_reward": -95.06675262946672,
    "episode_length": 512,
    "rlf_count": 23,
    "pp_count": 0,
    "ho_count": 20,
    "avg_reward_per_step": -0.1856772512294272,
    "entropy_coef": 0.0104,
    "ttt_final": 320,
    "hys_final": 2.5
  },
  {
    "episode": 310,
    "total_reward": 25.50440622275233,
    "episode_length": 512,
    "rlf_count": 0,
    "pp_count": 0,
    "ho_count": 1,
    "avg_reward_per_step": 0.049813293403813144,
    "entropy_coef": 0.01027142857142857,
    "ttt_final": 320,
    "hys_final": 2.5
  },
  {
    "episode": 311,
    "total_reward": 37.51262777182103,
    "episode_length": 512,
    "rlf_count": 0,
    "pp_count": 0,
    "ho_count": 4,
    "avg_reward_per_step": 0.07326685111683795,
    "entropy_coef": 0.010142857142857141,
    "ttt_final": 200,
    "hys_final": 2.0
  },
  {
    "episode": 312,
    "total_reward": 44.71556547187944,
    "episode_length": 512,
    "rlf_count": 0,
    "pp_count": 0,
    "ho_count": 1,
    "avg_reward_per_step": 0.08733508881226452,
    "entropy_coef": 0.010014285714285712,
    "ttt_final": 240,
    "hys_final": 2.0
  },
  {
    "episode": 313,
    "total_reward": 35.597575476103685,
    "episode_length": 512,
    "rlf_count": 0,
    "pp_count": 0,
    "ho_count": 1,
    "avg_reward_per_step": 0.06952651460176501,
    "entropy_coef": 0.009885714285714282,
    "ttt_final": 320,
    "hys_final": 2.0
  },
  {
    "episode": 314,
    "total_reward": 41.342950849178216,
    "episode_length": 512,
    "rlf_count": 0,
    "pp_count": 0,
    "ho_count": 1,
    "avg_reward_per_step": 0.0807479508773012,
    "entropy_coef": 0.00975714285714286,
    "ttt_final": 200,
    "hys_final": 2.5
  },
  {
    "episode": 315,
    "total_reward": 16.881732871147015,
    "episode_length": 512,
    "rlf_count": 0,
    "pp_count": 0,
    "ho_count": 3,
    "avg_reward_per_step": 0.032972134513959014,
    "entropy_coef": 0.009628571428571424,
    "ttt_final": 320,
    "hys_final": 2.0
  },
  {
    "episode": 316,
    "total_reward": 14.841752861365944,
    "episode_length": 512,
    "rlf_count": 0,
    "pp_count": 0,
    "ho_count": 3,
    "avg_reward_per_step": 0.02898779855735536,
    "entropy_coef": 0.009499999999999995,
    "ttt_final": 320,
    "hys_final": 2.0
  },
  {
    "episode": 317,
    "total_reward": 41.123459125451475,
    "episode_length": 512,
    "rlf_count": 0,
    "pp_count": 0,
    "ho_count": 2,
    "avg_reward_per_step": 0.08031925610439741,
    "entropy_coef": 0.009371428571428572,
    "ttt_final": 320,
    "hys_final": 2.0
  },
  {
    "episode": 318,
    "total_reward": 23.22793246323108,
    "episode_length": 512,
    "rlf_count": 0,
    "pp_count": 0,
    "ho_count": 5,
    "avg_reward_per_step": 0.045367055592248205,
    "entropy_coef": 0.009242857142857143,
    "ttt_final": 320,
    "hys_final": 2.0
  },
  {
    "episode": 319,
    "total_reward": 35.86496552650634,
    "episode_length": 512,
    "rlf_count": 0,
    "pp_count": 0,
    "ho_count": 2,
    "avg_reward_per_step": 0.07004876079395769,
    "entropy_coef": 0.009114285714285714,
    "ttt_final": 160,
    "hys_final": 2.0
  },
  {
    "episode": 320,
    "total_reward": 46.15168907316639,
    "episode_length": 512,
    "rlf_count": 0,
    "pp_count": 0,
    "ho_count": 0,
    "avg_reward_per_step": 0.0901400177210281,
    "entropy_coef": 0.008985714285714284,
    "ttt_final": 100,
    "hys_final": 2.0
  },
  {
    "episode": 321,
    "total_reward": 42.853943420038355,
    "episode_length": 512,
    "rlf_count": 0,
    "pp_count": 0,
    "ho_count": 0,
    "avg_reward_per_step": 0.08369910824226241,
    "entropy_coef": 0.008857142857142855,
    "ttt_final": 160,
    "hys_final": 2.0
  },
  {
    "episode": 322,
    "total_reward": 1.7578993398943985,
    "episode_length": 512,
    "rlf_count": 0,
    "pp_count": 5,
    "ho_count": 11,
    "avg_reward_per_step": 0.003433397148231247,
    "entropy_coef": 0.008728571428571426,
    "ttt_final": 240,
    "hys_final": 2.0
  },
  {
    "episode": 323,
    "total_reward": 28.309901857212633,
    "episode_length": 512,
    "rlf_count": 0,
    "pp_count": 0,
    "ho_count": 2,
    "avg_reward_per_step": 0.055292777064868424,
    "entropy_coef": 0.008599999999999997,
    "ttt_final": 160,
    "hys_final": 2.0
  },
  {
    "episode": 324,
    "total_reward": 47.75036873806764,
    "episode_length": 512,
    "rlf_count": 0,
    "pp_count": 0,
    "ho_count": 0,
    "avg_reward_per_step": 0.09326243894153836,
    "entropy_coef": 0.008471428571428574,
    "ttt_final": 160,
    "hys_final": 2.0
  },
  {
    "episode": 325,
    "total_reward": 17.030624653726033,
    "episode_length": 512,
    "rlf_count": 0,
    "pp_count": 0,
    "ho_count": 1,
    "avg_reward_per_step": 0.03326293877680866,
    "entropy_coef": 0.008342857142857138,
    "ttt_final": 100,
    "hys_final": 2.0
  },
  {
    "episode": 326,
    "total_reward": -59.12139920069951,
    "episode_length": 387,
    "rlf_count": 16,
    "pp_count": 2,
    "ho_count": 13,
    "avg_reward_per_step": -0.15276847338682042,
    "entropy_coef": 0.008214285714285709,
    "ttt_final": 320,
    "hys_final": 2.0
  },
  {
    "episode": 327,
    "total_reward": 48.17186178074673,
    "episode_length": 512,
    "rlf_count": 0,
    "pp_count": 0,
    "ho_count": 0,
    "avg_reward_per_step": 0.09408566754052096,
    "entropy_coef": 0.008085714285714286,
    "ttt_final": 160,
    "hys_final": 2.0
  },
  {
    "episode": 328,
    "total_reward": 38.101893595534655,
    "episode_length": 512,
    "rlf_count": 0,
    "pp_count": 0,
    "ho_count": 2,
    "avg_reward_per_step": 0.07441776092877862,
    "entropy_coef": 0.007957142857142857,
    "ttt_final": 100,
    "hys_final": 2.0
  },
  {
    "episode": 329,
    "total_reward": -49.72985682763078,
    "episode_length": 512,
    "rlf_count": 0,
    "pp_count": 2,
    "ho_count": 40,
    "avg_reward_per_step": -0.09712862661646637,
    "entropy_coef": 0.007828571428571428,
    "ttt_final": 320,
    "hys_final": 2.0
  },
  {
    "episode": 330,
    "total_reward": 33.33412375098548,
    "episode_length": 512,
    "rlf_count": 0,
    "pp_count": 0,
    "ho_count": 2,
    "avg_reward_per_step": 0.06510571045114352,
    "entropy_coef": 0.0076999999999999985,
    "ttt_final": 240,
    "hys_final": 2.0
  },
  {
    "episode": 331,
    "total_reward": 43.89862008270311,
    "episode_length": 512,
    "rlf_count": 0,
    "pp_count": 0,
    "ho_count": 0,
    "avg_reward_per_step": 0.08573949234902951,
    "entropy_coef": 0.007571428571428569,
    "ttt_final": 160,
    "hys_final": 2.0
  },
  {
    "episode": 332,
    "total_reward": 48.70154965758256,
    "episode_length": 512,
    "rlf_count": 0,
    "pp_count": 0,
    "ho_count": 0,
    "avg_reward_per_step": 0.09512021417496594,
    "entropy_coef": 0.00744285714285714,
    "ttt_final": 160,
    "hys_final": 2.0
  },
  {
    "episode": 333,
    "total_reward": 46.78324190859769,
    "episode_length": 512,
    "rlf_count": 0,
    "pp_count": 0,
    "ho_count": 0,
    "avg_reward_per_step": 0.09137351935272986,
    "entropy_coef": 0.007314285714285711,
    "ttt_final": 160,
    "hys_final": 2.0
  },
  {
    "episode": 334,
    "total_reward": -86.76469180181326,
    "episode_length": 512,
    "rlf_count": 28,
    "pp_count": 1,
    "ho_count": 16,
    "avg_reward_per_step": -0.16946228867541652,
    "entropy_coef": 0.007185714285714281,
    "ttt_final": 320,
    "hys_final": 2.0
  },
  {
    "episode": 335,
    "total_reward": 8.166263890614779,
    "episode_length": 512,
    "rlf_count": 0,
    "pp_count": 0,
    "ho_count": 9,
    "avg_reward_per_step": 0.01594973416135699,
    "entropy_coef": 0.007057142857142852,
    "ttt_final": 320,
    "hys_final": 2.0
  },
  {
    "episode": 336,
    "total_reward": 38.47048686789164,
    "episode_length": 512,
    "rlf_count": 0,
    "pp_count": 0,
    "ho_count": 4,
    "avg_reward_per_step": 0.07513766966385085,
    "entropy_coef": 0.006928571428571423,
    "ttt_final": 160,
    "hys_final": 2.0
  },
  {
    "episode": 337,
    "total_reward": 43.182714509231324,
    "episode_length": 512,
    "rlf_count": 0,
    "pp_count": 0,
    "ho_count": 0,
    "avg_reward_per_step": 0.08434123927584243,
    "entropy_coef": 0.0068000000000000005,
    "ttt_final": 160,
    "hys_final": 2.0
  },
  {
    "episode": 338,
    "total_reward": 9.567768323612773,
    "episode_length": 325,
    "rlf_count": 0,
    "pp_count": 0,
    "ho_count": 5,
    "avg_reward_per_step": 0.029439287149577765,
    "entropy_coef": 0.006671428571428571,
    "ttt_final": 240,
    "hys_final": 2.5
  },
  {
    "episode": 339,
    "total_reward": 20.676509786256965,
    "episode_length": 512,
    "rlf_count": 0,
    "pp_count": 0,
    "ho_count": 6,
    "avg_reward_per_step": 0.040383808176283134,
    "entropy_coef": 0.006542857142857142,
    "ttt_final": 320,
    "hys_final": 2.0
  },
  {
    "episode": 340,
    "total_reward": -3.0362969497246075,
    "episode_length": 512,
    "rlf_count": 0,
    "pp_count": 3,
    "ho_count": 15,
    "avg_reward_per_step": -0.005930267479930874,
    "entropy_coef": 0.006414285714285713,
    "ttt_final": 320,
    "hys_final": 2.0
  },
  {
    "episode": 341,
    "total_reward": 16.232724201613376,
    "episode_length": 512,
    "rlf_count": 0,
    "pp_count": 0,
    "ho_count": 8,
    "avg_reward_per_step": 0.031704539456276125,
    "entropy_coef": 0.006285714285714283,
    "ttt_final": 320,
    "hys_final": 2.0
  },
  {
    "episode": 342,
    "total_reward": 46.222745290469796,
    "episode_length": 512,
    "rlf_count": 0,
    "pp_count": 0,
    "ho_count": 0,
    "avg_reward_per_step": 0.09027879939544882,
    "entropy_coef": 0.006157142857142854,
    "ttt_final": 160,
    "hys_final": 2.0
  },
  {
    "episode": 343,
    "total_reward": 37.810962099563106,
    "episode_length": 512,
    "rlf_count": 0,
    "pp_count": 0,
    "ho_count": 1,
    "avg_reward_per_step": 0.07384953535070919,
    "entropy_coef": 0.006028571428571432,
    "ttt_final": 240,
    "hys_final": 2.0
  },
  {
    "episode": 344,
    "total_reward": 31.891116594758614,
    "episode_length": 512,
    "rlf_count": 0,
    "pp_count": 0,
    "ho_count": 1,
    "avg_reward_per_step": 0.06228733709913792,
    "entropy_coef": 0.0058999999999999955,
    "ttt_final": 240,
    "hys_final": 2.0
  },
  {
    "episode": 345,
    "total_reward": -10.550023591512508,
    "episode_length": 512,
    "rlf_count": 0,
    "pp_count": 3,
    "ho_count": 16,
    "avg_reward_per_step": -0.020605514827172867,
    "entropy_coef": 0.005771428571428566,
    "ttt_final": 160,
    "hys_final": 2.0
  },
  {
    "episode": 346,
    "total_reward": 44.0156418685154,
    "episode_length": 512,
    "rlf_count": 0,
    "pp_count": 0,
    "ho_count": 2,
    "avg_reward_per_step": 0.08596805052444415,
    "entropy_coef": 0.005642857142857137,
    "ttt_final": 200,
    "hys_final": 2.0
  },
  {
    "episode": 347,
    "total_reward": 37.932432892966276,
    "episode_length": 512,
    "rlf_count": 0,
    "pp_count": 0,
    "ho_count": 0,
    "avg_reward_per_step": 0.07408678299407476,
    "entropy_coef": 0.005514285714285715,
    "ttt_final": 160,
    "hys_final": 2.0
  },
  {
    "episode": 348,
    "total_reward": 28.52909049595043,
    "episode_length": 512,
    "rlf_count": 0,
    "pp_count": 1,
    "ho_count": 5,
    "avg_reward_per_step": 0.055720879874903186,
    "entropy_coef": 0.005385714285714285,
    "ttt_final": 320,
    "hys_final": 2.0
  },
  {
    "episode": 349,
    "total_reward": 24.881155289706474,
    "episode_length": 512,
    "rlf_count": 0,
    "pp_count": 0,
    "ho_count": 2,
    "avg_reward_per_step": 0.048596006425207956,
    "entropy_coef": 0.005257142857142856,
    "ttt_final": 240,
    "hys_final": 2.0
  },
  {
    "episode": 350,
    "total_reward": 35.09121694054035,
    "episode_length": 512,
    "rlf_count": 0,
    "pp_count": 0,
    "ho_count": 4,
    "avg_reward_per_step": 0.06853753308699287,
    "entropy_coef": 0.005128571428571427,
    "ttt_final": 240,
    "hys_final": 2.0
  }
]